Workbook
Name IQ_CH: 110000
Name IQ_CQ: 5000
Name IQ_CY: 10000
Name IQ_DAILY: 500000
Name IQ_FH: 100000
Name IQ_FQ: 500
Name IQ_FY: 1000
Name IQ_LTM: 2000
Name IQ_MONTH: 15000
Name IQ_NTM: 6000
Name IQ_WEEK: 50000
Name IQ_YTD: 3000
Name UPDATE: 'Data Sheet'!$E$1

Sheet Data>

Sheet Football Field Analysis
L4: Fooball Field Analysis - Data
N5: Open Low | O5: Low | P5: Open High | Q5: High
L6: Relative Valuation | N6: 3996.3478 | O6: =N6 -> 3996.3478 | P6: 4543.4868 | Q6: =P6 -> 4543.4868
L7: DCF Bear | N7: ='DCF>'!J17 -> 2312.0488 | O7: =N7 -> 2312.0488 | P7: ='DCF>'!J22 -> 3501.4767 | Q7: =P7 -> 3501.4767
L8: DCF Base | N8: ='DCF>'!H17 -> 2719.2986 | O8: =N8 -> 2719.2986 | P8: ='DCF>'!H22 -> 4633.7206 | Q8: =P8 -> 4633.7206
L9: DCF Bull | N9: ='DCF>'!G17 -> 2774.6041 | O9: =N9 -> 2774.6041 | P9: ='DCF>'!G22 -> 4809.8474 | Q9: =P9 -> 4809.8474
L10: 52 Weeks Range | N10: 3288 | O10: =N10 -> 3288 | P10: 4440 | Q10: =P10 -> 4440

Sheet VAR
B1: 10 Year -Daily
B3: Date | C3: Price | D3: Returns | E3: Shorted Returns | G3: Replication | H3: Simulated Returns | J3: ="Calculation of Value at Risk - "&'Data Sheet'!B1&" (Historical)" -> Calculation of Value at Risk - LARSEN & TOUBRO LTD (Historical)
B4: 07/30/2026 | C4: 3937.7 | D4: =(C4-C5)/C5 -> 0.0016024826 | E4: 0.094096579 | G4: 1 | H4: =_xlfn.NORM.INV(RAND(),N$6,N$7) -> 0.018039772
B5: 07/29/2026 | C5: 3931.4 | D5: =(C5-C6)/C6 -> 0.025939457 | E5: 0.086503906 | G5: 2 | H5: =_xlfn.NORM.INV(RAND(),N$6,N$7) -> -0.0071208774 | J5: Historical Approach
B6: 07/28/2026 | C6: 3832 | D6: =(C6-C7)/C7 -> 0.006831319 | E6: 0.080221478 | G6: 3 | H6: =_xlfn.NORM.INV(RAND(),N$6,N$7) -> 0.013811151 | J6: Mean | N6: =AVERAGE(E4:E2478) -> 0.0035224209
B7: 07/27/2026 | C7: 3806 | D7: =(C7-C8)/C8 -> 0.0053888419 | E7: 0.075501428 | G7: 4 | H7: =_xlfn.NORM.INV(RAND(),N$6,N$7) -> 0.0049694011 | J7: Std | N7: =_xlfn.STDEV.S(E4:E2478) -> 0.012256623
B8: 07/24/2026 | C8: 3785.6 | D8: =(C8-C9)/C9 -> -0.0017930598 | E8: 0.071999046 | G8: 5 | H8: =_xlfn.NORM.INV(RAND(),N$6,N$7) -> -0.012831709 | J8: Min | N8: =MIN(E4:E2478) -> -0.016003174
B9: 07/23/2026 | C9: 3792.4 | D9: =(C9-C10)/C10 -> -0.00654896 | E9: 0.062391824 | G9: 6 | H9: =_xlfn.NORM.INV(RAND(),N$6,N$7) -> -0.0038322028 | J9: Max | N9: =MAX(E4:E2478) -> 0.094096579
B10: 07/22/2026 | C10: 3817.4 | D10: =(C10-C11)/C11 -> -0.0075911194 | E10: 0.060686915 | G10: 7 | H10: =_xlfn.NORM.INV(RAND(),N$6,N$7) -> 0.014922165 | J10: current Price | N10: ='Data Sheet'!B8 -> 3785.6
B11: 07/21/2026 | C11: 3846.6 | D11: =(C11-C12)/C12 -> 0.002031885 | E11: 0.060481307 | G11: 8 | H11: =_xlfn.NORM.INV(RAND(),N$6,N$7) -> 0.016599918
B12: 07/20/2026 | C12: 3838.8 | D12: =(C12-C13)/C13 -> 0.0063704286 | E12: 0.059315661 | G12: 9 | H12: =_xlfn.NORM.INV(RAND(),N$6,N$7) -> 0.0015517221 | J12: Percentile | K12: Confidence | L12: VAR% | M12: Stock Price | N12: VAR(INR)
B13: 07/17/2026 | C13: 3814.5 | D13: =(C13-C14)/C14 -> 0.010302998 | E13: 0.053850661 | G13: 10 | H13: =_xlfn.NORM.INV(RAND(),N$6,N$7) -> 0.0052614491 | J13: 0.05 | K13: =100%-J13 -> 0.95 | L13: =_xlfn.PERCENTILE.INC($E$4:$E$2746,J13) -> -0.012453054 | M13: =$N$10*(1-L13) -> 3832.7423 | N13: =$N$10-M13 -> -47.142283
B14: 07/16/2026 | C14: 3775.6 | D14: =(C14-C15)/C15 -> -0.0021935041 | E14: 0.053000817 | G14: 11 | H14: =_xlfn.NORM.INV(RAND(),N$6,N$7) -> 0.0077315897 | J14: 0.01 | K14: =100%-J14 -> 0.99 | L14: =_xlfn.PERCENTILE.INC($E$4:$E$2746,J14) -> -0.015081558 | M14: =$N$10*(1-L14) -> 3842.6927 | N14: =$N$10-M14 -> -57.092747
B15: 07/15/2026 | C15: 3783.9 | D15: =(C15-C16)/C16 -> -0.016836854 | E15: 0.050872278 | G15: 12 | H15: =_xlfn.NORM.INV(RAND(),N$6,N$7) -> 0.013787907 | J15: 0.005 | K15: =100%-J15 -> 0.995 | L15: =_xlfn.PERCENTILE.INC($E$4:$E$2746,J15) -> -0.015387607 | M15: =$N$10*(1-L15) -> 3843.8513 | N15: =$N$10-M15 -> -58.251325
B16: 07/14/2026 | C16: 3848.7 | D16: =(C16-C17)/C17 -> -0.020313097 | E16: 0.04893431 | G16: 13 | H16: =_xlfn.NORM.INV(RAND(),N$6,N$7) -> 0.018668191
B17: 07/13/2026 | C17: 3928.5 | D17: =(C17-C18)/C18 -> -0.0043844087 | E17: 0.048096527 | G17: 14 | H17: =_xlfn.NORM.INV(RAND(),N$6,N$7) -> -0.0013209399 | J17: Monte Carlo Simulation
B18: 46302 | C18: 3945.8 | D18: =(C18-C19)/C19 -> 0.015388574 | E18: 0.048056312 | G18: 15 | H18: =_xlfn.NORM.INV(RAND(),N$6,N$7) -> -0.01477001 | J18: Mean | N18: =AVERAGE(H4:H5003) -> 0.0035851673
B19: 46272 | C19: 3886 | D19: =(C19-C20)/C20 -> -0.0015672773 | E19: 0.047002316 | G19: 16 | H19: =_xlfn.NORM.INV(RAND(),N$6,N$7) -> 0.016487386 | J19: Std | N19: =_xlfn.STDEV.S(H4:H5003) -> 0.012184159
B20: 46241 | C20: 3892.1 | D20: =(C20-C21)/C21 -> -0.025000626 | E20: 0.046593579 | G20: 17 | H20: =_xlfn.NORM.INV(RAND(),N$6,N$7) -> -0.0061844341 | J20: Min | N20: =MIN(H4:H5003) -> -0.038015071
B21: 46210 | C21: 3991.9 | D21: =(C21-C22)/C22 -> -0.012150458 | E21: 0.045199699 | G21: 18 | H21: =_xlfn.NORM.INV(RAND(),N$6,N$7) -> 0.0034622514 | J21: Max | N21: =MAX(H4:H5003) -> 0.047476494
B22: 46180 | C22: 4041 | D22: =(C22-C23)/C23 -> 0.0035762181 | E22: 0.04509434 | G22: 19 | H22: =_xlfn.NORM.INV(RAND(),N$6,N$7) -> 0.016295177 | J22: current Price | N22: =N10 -> 3785.6
B23: 46088 | C23: 4026.6 | D23: =(C23-C24)/C24 -> -0.0080800118 | E23: 0.044805974 | G23: 20 | H23: =_xlfn.NORM.INV(RAND(),N$6,N$7) -> -0.015977448
B24: 46060 | C24: 4059.4 | D24: =(C24-C25)/C25 -> -0.0081122025 | E24: 0.044711703 | G24: 21 | H24: =_xlfn.NORM.INV(RAND(),N$6,N$7) -> 0.00094710541 | J24: Percentile | K24: Confidence | L24: VAR% | M24: Stock Price | N24: VAR(INR)
B25: 46029 | C25: 4092.6 | D25: =(C25-C26)/C26 -> -0.012260462 | E25: 0.044688134 | G25: 22 | H25: =_xlfn.NORM.INV(RAND(),N$6,N$7) -> -0.0048509767 | J25: 0.05 | K25: =100%-J25 -> 0.95 | L25: =_xlfn.PERCENTILE.INC($H$4:$H$5003,J25) -> -0.016485083 | M25: =$N$10*(1-L25) -> 3848.0059 | N25: =$N$10-M25 -> -62.405932
B26: 06/30/2026 | C26: 4143.4 | D26: =(C26-C27)/C27 -> -0.0052338423 | E26: 0.043709948 | G26: 23 | H26: =_xlfn.NORM.INV(RAND(),N$6,N$7) -> 0.0044366711 | J26: 0.01 | K26: =100%-J26 -> 0.99 | L26: =_xlfn.PERCENTILE.INC($H$4:$H$5003,J26) -> -0.023919452 | M26: =$N$10*(1-L26) -> 3876.1495 | N26: =$N$10-M26 -> -90.549477
B27: 06/29/2026 | C27: 4165.2 | D27: =(C27-C28)/C28 -> -0.01214306 | E27: 0.043314073 | G27: 24 | H27: =_xlfn.NORM.INV(RAND(),N$6,N$7) -> 0.0015757503 | J27: 0.005 | K27: =100%-J27 -> 0.995 | L27: =_xlfn.PERCENTILE.INC($H$4:$H$5003,J27) -> -0.026472369 | M27: =$N$10*(1-L27) -> 3885.8138 | N27: =$N$10-M27 -> -100.2138
B28: 06/25/2026 | C28: 4216.4 | D28: =(C28-C29)/C29 -> 0.0082980606 | E28: 0.043241171 | G28: 25 | H28: =_xlfn.NORM.INV(RAND(),N$6,N$7) -> -0.0015729193
B29: 06/24/2026 | C29: 4181.7 | D29: =(C29-C30)/C30 -> 0.00055031823 | E29: 0.042689967 | G29: 26 | H29: =_xlfn.NORM.INV(RAND(),N$6,N$7) -> -0.00052404998
B30: 06/23/2026 | C30: 4179.4 | D30: =(C30-C31)/C31 -> -0.0052126723 | E30: 0.042510041 | G30: 27 | H30: =_xlfn.NORM.INV(RAND(),N$6,N$7) -> -0.0064035008
B31: 06/22/2026 | C31: 4201.3 | D31: =(C31-C32)/C32 -> -0.0019242647 | E31: 0.042413309 | G31: 28 | H31: =_xlfn.NORM.INV(RAND(),N$6,N$7) -> -0.00028814448
B32: 06/19/2026 | C32: 4209.4 | D32: =(C32-C33)/C33 -> 0.0046300716 | E32: 0.042215201 | G32: 29 | H32: =_xlfn.NORM.INV(RAND(),N$6,N$7) -> -0.016966405
B33: 06/18/2026 | C33: 4190 | D33: =(C33-C34)/C34 -> -0.0042065737 | E33: 0.041911211 | G33: 30 | H33: =_xlfn.NORM.INV(RAND(),N$6,N$7) -> 0.015715991
B34: 06/17/2026 | C34: 4207.7 | D34: =(C34-C35)/C35 -> 0.0050879037 | E34: 0.041232582 | G34: 31 | H34: =_xlfn.NORM.INV(RAND(),N$6,N$7) -> 0.011759661
B35: 06/16/2026 | C35: 4186.4 | D35: =(C35-C36)/C36 -> 0.0039810063 | E35: 0.041024825 | G35: 32 | H35: =_xlfn.NORM.INV(RAND(),N$6,N$7) -> -0.012227027
B36: 06/15/2026 | C36: 4169.8 | D36: =(C36-C37)/C37 -> 0.02975823 | E36: 0.04047619 | G36: 33 | H36: =_xlfn.NORM.INV(RAND(),N$6,N$7) -> 0.023489395
B37: 46362 | C37: 4049.3 | D37: =(C37-C38)/C38 -> 0.048498187 | E37: 0.039967438 | G37: 34 | H37: =_xlfn.NORM.INV(RAND(),N$6,N$7) -> 0.00037238239
B38: 46332 | C38: 3862 | D38: =(C38-C39)/C39 -> -0.014167198 | E38: 0.039910666 | G38: 35 | H38: =_xlfn.NORM.INV(RAND(),N$6,N$7) -> 0.015487912
B39: 46301 | C39: 3917.5 | D39: =(C39-C40)/C40 -> 0.0043326668 | E39: 0.039122237 | G39: 36 | H39: =_xlfn.NORM.INV(RAND(),N$6,N$7) -> -0.014105121
B40: 46271 | C40: 3900.6 | D40: =(C40-C41)/C41 -> 0.0064765837 | E40: 0.039016569 | G40: 37 | H40: =_xlfn.NORM.INV(RAND(),N$6,N$7) -> -0.013297713
B41: 46240 | C41: 3875.5 | D41: =(C41-C42)/C42 -> -0.019654963 | E41: 0.038953686 | G41: 38 | H41: =_xlfn.NORM.INV(RAND(),N$6,N$7) -> 0.00089242259
B42: 46148 | C42: 3953.2 | D42: =(C42-C43)/C43 -> 0.0028157581 | E42: 0.038402173 | G42: 39 | H42: =_xlfn.NORM.INV(RAND(),N$6,N$7) -> -0.010766959
B43: 46118 | C43: 3942.1 | D43: =(C43-C44)/C44 -> -0.0028078519 | E43: 0.038383765 | G43: 40 | H43: =_xlfn.NORM.INV(RAND(),N$6,N$7) -> 0.0058801008
B44: 46087 | C44: 3953.2 | D44: =(C44-C45)/C45 -> -0.011922317 | E44: 0.038081684 | G44: 41 | H44: =_xlfn.NORM.INV(RAND(),N$6,N$7) -> 0.032514996
B45: 46059 | C45: 4000.9 | D45: =(C45-C46)/C46 -> -0.0024683355 | E45: 0.037635371 | G45: 42 | H45: =_xlfn.NORM.INV(RAND(),N$6,N$7) -> 0.023369122
B46: 46028 | C46: 4010.8 | D46: =(C46-C47)/C47 -> -0.016116767 | E46: 0.03761106 | G46: 43 | H46: =_xlfn.NORM.INV(RAND(),N$6,N$7) -> 0.0070251053
B47: 05/29/2026 | C47: 4076.5 | D47: =(C47-C48)/C48 -> 0.0071649166 | E47: 0.036951397 | G47: 44 | H47: =_xlfn.NORM.INV(RAND(),N$6,N$7) -> 0.024662316
B48: 05/27/2026 | C48: 4047.5 | D48: =(C48-C49)/C49 -> 0.0024022983 | E48: 0.036921274 | G48: 45 | H48: =_xlfn.NORM.INV(RAND(),N$6,N$7) -> -0.0089672181
B49: 05/26/2026 | C49: 4037.8 | D49: =(C49-C50)/C50 -> 0.0010908911 | E49: 0.036688546 | G49: 46 | H49: =_xlfn.NORM.INV(RAND(),N$6,N$7) -> -0.0069824779
B50: 05/25/2026 | C50: 4033.4 | D50: =(C50-C51)/C51 -> 0.027199104 | E50: 0.036622834 | G50: 47 | H50: =_xlfn.NORM.INV(RAND(),N$6,N$7) -> 0.01088728
B51: 05/22/2026 | C51: 3926.6 | D51: =(C51-C52)/C52 -> -0.00048364516 | E51: 0.036619554 | G51: 48 | H51: =_xlfn.NORM.INV(RAND(),N$6,N$7) -> 0.0061127595
B52: 05/21/2026 | C52: 3928.5 | D52: =(C52-C53)/C53 -> 0.0045516148 | E52: 0.036434089 | G52: 49 | H52: =_xlfn.NORM.INV(RAND(),N$6,N$7) -> -0.0055368436
B53: 05/20/2026 | C53: 3910.7 | D53: =(C53-C54)/C54 -> -0.0026268809 | E53: 0.036363008 | G53: 50 | H53: =_xlfn.NORM.INV(RAND(),N$6,N$7) -> -0.0045553271
B54: 05/19/2026 | C54: 3921 | D54: =(C54-C55)/C55 -> 0.00081678493 | E54: 0.0362899 | G54: 51 | H54: =_xlfn.NORM.INV(RAND(),N$6,N$7) -> 0.0081922625
B55: 05/18/2026 | C55: 3917.8 | D55: =(C55-C56)/C56 -> 0.0022512151 | E55: 0.036223334 | G55: 52 | H55: =_xlfn.NORM.INV(RAND(),N$6,N$7) -> 0.010624948
B56: 05/15/2026 | C56: 3909 | D56: =(C56-C57)/C57 -> -0.0079687341 | E56: 0.036132017 | G56: 53 | H56: =_xlfn.NORM.INV(RAND(),N$6,N$7) -> -0.0066302799
B57: 05/14/2026 | C57: 3940.4 | D57: =(C57-C58)/C58 -> 0.0062822412 | E57: 0.035962541 | G57: 54 | H57: =_xlfn.NORM.INV(RAND(),N$6,N$7) -> 0.017398154
B58: 05/13/2026 | C58: 3915.8 | D58: =(C58-C59)/C59 -> 0.015376637 | E58: 0.035942004 | G58: 55 | H58: =_xlfn.NORM.INV(RAND(),N$6,N$7) -> 0.014253348
B59: 46361 | C59: 3856.5 | D59: =(C59-C60)/C60 -> -0.021242577 | E59: 0.035877043 | G59: 56 | H59: =_xlfn.NORM.INV(RAND(),N$6,N$7) -> 0.0044318217
B60: 46331 | C60: 3940.2 | D60: =(C60-C61)/C61 -> -0.0086300164 | E60: 0.035777094 | G60: 57 | H60: =_xlfn.NORM.INV(RAND(),N$6,N$7) -> 0.0091470713
B61: 46239 | C61: 3974.5 | D61: =(C61-C62)/C62 -> -0.01205568 | E61: 0.035731983 | G61: 58 | H61: =_xlfn.NORM.INV(RAND(),N$6,N$7) -> 0.021612132
B62: 46208 | C62: 4023 | D62: =(C62-C63)/C63 -> 0.0036173132 | E62: 0.034974738 | G62: 59 | H62: =_xlfn.NORM.INV(RAND(),N$6,N$7) -> -0.0012047077
B63: 46178 | C63: 4008.5 | D63: =(C63-C64)/C64 -> -0.011345419 | E63: 0.034767995 | G63: 60 | H63: =_xlfn.NORM.INV(RAND(),N$6,N$7) -> 0.011780579
B64: 46147 | C64: 4054.5 | D64: =(C64-C65)/C65 -> -0.01129048 | E64: 0.03476141 | G64: 61 | H64: =_xlfn.NORM.INV(RAND(),N$6,N$7) -> 0.011598238
B65: 46117 | C65: 4100.8 | D65: =(C65-C66)/C66 -> 0.021624315 | E65: 0.034493735 | G65: 62 | H65: =_xlfn.NORM.INV(RAND(),N$6,N$7) -> 0.017197746
B66: 04/30/2026 | C66: 4014 | D66: =(C66-C67)/C67 -> -0.020043456 | E66: 0.034404496 | G66: 63 | H66: =_xlfn.NORM.INV(RAND(),N$6,N$7) -> 0.01529484
B67: 04/29/2026 | C67: 4096.1 | D67: =(C67-C68)/C68 -> 0.01446368 | E67: 0.034190183 | G67: 64 | H67: =_xlfn.NORM.INV(RAND(),N$6,N$7) -> 0.0010011894
B68: 04/28/2026 | C68: 4037.7 | D68: =(C68-C69)/C69 -> -0.0039224393 | E68: 0.034106991 | G68: 65 | H68: =_xlfn.NORM.INV(RAND(),N$6,N$7) -> -0.01650536
B69: 04/27/2026 | C69: 4053.6 | D69: =(C69-C70)/C70 -> 0.0097900007 | E69: 0.034047971 | G69: 66 | H69: =_xlfn.NORM.INV(RAND(),N$6,N$7) -> -0.020496082
B70: 04/24/2026 | C70: 4014.3 | D70: =(C70-C71)/C71 -> -0.0098172221 | E70: 0.034029886 | G70: 67 | H70: =_xlfn.NORM.INV(RAND(),N$6,N$7) -> 0.01032578
B71: 04/23/2026 | C71: 4054.1 | D71: =(C71-C72)/C72 -> 0.0082067096 | E71: 0.033947014 | G71: 68 | H71: =_xlfn.NORM.INV(RAND(),N$6,N$7) -> -0.0035032191
B72: 04/22/2026 | C72: 4021.1 | D72: =(C72-C73)/C73 -> -0.013323846 | E72: 0.033426971 | G72: 69 | H72: =_xlfn.NORM.INV(RAND(),N$6,N$7) -> 0.012669823
B73: 04/21/2026 | C73: 4075.4 | D73: =(C73-C74)/C74 -> 0.0060232041 | E73: 0.03320646 | G73: 70 | H73: =_xlfn.NORM.INV(RAND(),N$6,N$7) -> -0.0091304187
B74: 04/20/2026 | C74: 4051 | D74: =(C74-C75)/C75 -> -0.011010473 | E74: 0.033009316 | G74: 71 | H74: =_xlfn.NORM.INV(RAND(),N$6,N$7) -> -0.023207769
B75: 04/17/2026 | C75: 4096.1 | D75: =(C75-C76)/C76 -> -0.0057527064 | E75: 0.032809799 | G75: 72 | H75: =_xlfn.NORM.INV(RAND(),N$6,N$7) -> -0.0061915724
B76: 04/16/2026 | C76: 4119.8 | D76: =(C76-C77)/C77 -> 0.010671442 | E76: 0.032798442 | G76: 73 | H76: =_xlfn.NORM.INV(RAND(),N$6,N$7) -> -0.016607432
B77: 04/15/2026 | C77: 4076.3 | D77: =(C77-C78)/C78 -> 0.03085249 | E77: 0.032668363 | G77: 74 | H77: =_xlfn.NORM.INV(RAND(),N$6,N$7) -> 0.01224487
B78: 04/13/2026 | C78: 3954.3 | D78: =(C78-C79)/C79 -> -0.0014141771 | E78: 0.032559892 | G78: 75 | H78: =_xlfn.NORM.INV(RAND(),N$6,N$7) -> 0.011968521
B79: 46299 | C79: 3959.9 | D79: =(C79-C80)/C80 -> 0.016349263 | E79: 0.032423208 | G79: 76 | H79: =_xlfn.NORM.INV(RAND(),N$6,N$7) -> 0.01298034
B80: 46269 | C80: 3896.2 | D80: =(C80-C81)/C81 -> -0.027384608 | E80: 0.032115046 | G80: 77 | H80: =_xlfn.NORM.INV(RAND(),N$6,N$7) -> 0.0024797535
B81: 46238 | C81: 4005.9 | D81: =(C81-C82)/C82 -> 0.075900411 | E81: 0.032113584 | G81: 78 | H81: =_xlfn.NORM.INV(RAND(),N$6,N$7) -> -0.0046188662
B82: 46207 | C82: 3723.3 | D82: =(C82-C83)/C83 -> -0.0011803525 | E82: 0.032073382 | G82: 79 | H82: =_xlfn.NORM.INV(RAND(),N$6,N$7) -> -0.0019820142
B83: 46177 | C83: 3727.7 | D83: =(C83-C84)/C84 -> 0.031717915 | E83: 0.031817614 | G83: 80 | H83: =_xlfn.NORM.INV(RAND(),N$6,N$7) -> 0.016071313
B84: 46057 | C84: 3613.1 | D84: =(C84-C85)/C85 -> 0.0015523216 | E84: 0.031531377 | G84: 81 | H84: =_xlfn.NORM.INV(RAND(),N$6,N$7) -> -0.012905321
B85: 46026 | C85: 3607.5 | D85: =(C85-C86)/C86 -> 0.02950829 | E85: 0.031441547 | G85: 82 | H85: =_xlfn.NORM.INV(RAND(),N$6,N$7) -> -2.5998593e-05
B86: 03/30/2026 | C86: 3504.1 | D86: =(C86-C87)/C87 -> -0.016834544 | E86: 0.031169586 | G86: 83 | H86: =_xlfn.NORM.INV(RAND(),N$6,N$7) -> -0.028125996
B87: 03/27/2026 | C87: 3564.1 | D87: =(C87-C88)/C88 -> -0.023346943 | E87: 0.031114019 | G87: 84 | H87: =_xlfn.NORM.INV(RAND(),N$6,N$7) -> 0.013112604
B88: 03/25/2026 | C88: 3649.3 | D88: =(C88-C89)/C89 -> 0.037676297 | E88: 0.031035067 | G88: 85 | H88: =_xlfn.NORM.INV(RAND(),N$6,N$7) -> 0.018529405
B89: 03/24/2026 | C89: 3516.8 | D89: =(C89-C90)/C90 -> 0.052178076 | E89: 0.030963303 | G89: 86 | H89: =_xlfn.NORM.INV(RAND(),N$6,N$7) -> -0.0068666115
B90: 03/23/2026 | C90: 3342.4 | D90: =(C90-C91)/C91 -> -0.02690113 | E90: 0.030918881 | G90: 87 | H90: =_xlfn.NORM.INV(RAND(),N$6,N$7) -> 0.00082621655
B91: 03/20/2026 | C91: 3434.8 | D91: =(C91-C92)/C92 -> 8.7348959e-05 | E91: 0.030666913 | G91: 88 | H91: =_xlfn.NORM.INV(RAND(),N$6,N$7) -> 0.011650908
B92: 03/19/2026 | C92: 3434.5 | D92: =(C92-C93)/C93 -> -0.048061199 | E92: 0.030636095 | G92: 89 | H92: =_xlfn.NORM.INV(RAND(),N$6,N$7) -> 0.015131499
B93: 03/18/2026 | C93: 3607.9 | D93: =(C93-C94)/C94 -> 0.018375296 | E93: 0.030511355 | G93: 90 | H93: =_xlfn.NORM.INV(RAND(),N$6,N$7) -> -0.0075392706
B94: 03/17/2026 | C94: 3542.8 | D94: =(C94-C95)/C95 -> 0.021156396 | E94: 0.030486315 | G94: 91 | H94: =_xlfn.NORM.INV(RAND(),N$6,N$7) -> 0.0056699851
B95: 03/16/2026 | C95: 3469.4 | D95: =(C95-C96)/C96 -> 0.008839779 | E95: 0.030442765 | G95: 92 | H95: =_xlfn.NORM.INV(RAND(),N$6,N$7) -> 0.0091940929
B96: 03/13/2026 | C96: 3439 | D96: =(C96-C97)/C97 -> -0.075413362 | E96: 0.03034238 | G96: 93 | H96: =_xlfn.NORM.INV(RAND(),N$6,N$7) -> 0.023634695
B97: 46359 | C97: 3719.5 | D97: =(C97-C98)/C98 -> -0.03107742 | E97: 0.030096849 | G97: 94 | H97: =_xlfn.NORM.INV(RAND(),N$6,N$7) -> 0.007147406
B98: 46329 | C98: 3838.8 | D98: =(C98-C99)/C99 -> -0.0095975232 | E98: 0.030064453 | G98: 95 | H98: =_xlfn.NORM.INV(RAND(),N$6,N$7) -> 0.0054458252
B99: 46298 | C99: 3876 | D99: =(C99-C100)/C100 -> 0.0088232998 | E99: 0.02992753 | G99: 96 | H99: =_xlfn.NORM.INV(RAND(),N$6,N$7) -> 0.0056763684
B100: 46268 | C100: 3842.1 | D100: =(C100-C101)/C101 -> -0.027267203 | E100: 0.029763838 | G100: 97 | H100: =_xlfn.NORM.INV(RAND(),N$6,N$7) -> 0.015281527
B101: 46176 | C101: 3949.8 | D101: =(C101-C102)/C102 -> -0.022012034 | E101: 0.029600374 | G101: 98 | H101: =_xlfn.NORM.INV(RAND(),N$6,N$7) -> -0.0062414921
...

Sheet Altman Z Score
B3: ='Data Sheet'!B1 -> LARSEN & TOUBRO LTD
B4: =CONCATENATE("(",_xlfn.XLOOKUP(B3,'List Of Stocks'!B2:B5442,'List Of Stocks'!D2:D5442)," ","|"," ","BSE Code:"," ",_xlfn.XLOOKUP('Altman Z Score'!B3,'List Of Stocks'!B2:B5442,'List Of Stocks'!C2:C5442)," ",")") -> (LT | BSE Code: 500510 )
B5: =CONCATENATE("INR"," ",'Data Sheet'!B8) -> INR 3785.6
B6: ="52 Week"&" "&"("&"High -"&" INR "&'Football Field Analysis'!Q10&" "&"LOW - "&" INR "&'Football Field Analysis'!N10&")" -> 52 Week (High - INR 4440 LOW - INR 3288)
B8: Altman's Z Score Analysis
B9: Larsen & Toubro Limited (L&T) is an Indian multinational conglomerate headquartered in Mumbai. It operates in sectors including industrial technology, heavy industry, engineering, construction, manufacturing, power, information technology, defence, and financial services. L&T was founded in 1938 in Bombay by Danish engineers Henning Holck-Larsen and Søren Kristian Toubro. As of 31 March 2022, the L&T Group consisted of 93 subsidiaries, 5 associate companies, 27 joint ventures, and 35 joint operations. As of 1 October 2023, S N Subrahmanyan serves as the chairman and managing director of L&T, having succeeded A M Naik.
B16: Financial Summary
B67: Working Capital/Total Assets
C68: =HistoricalFS!F3 -> 43921 | D68: =HistoricalFS!G3 -> 44286 | E68: =HistoricalFS!H3 -> 44651 | F68: =HistoricalFS!I3 -> 45016 | G68: =HistoricalFS!J3 -> 45382 | H68: =HistoricalFS!K3 -> 45747 | I68: =HistoricalFS!L3 -> 46112
B69: Working Capital | C69: ='Data Sheet'!E65-'Data Sheet'!E60 -> 142884.94 | D69: ='Data Sheet'!F65-'Data Sheet'!F60 -> 126051.27 | E69: ='Data Sheet'!G65-'Data Sheet'!G60 -> 124326 | F69: ='Data Sheet'!H65-'Data Sheet'!H60 -> 119471.51 | G69: ='Data Sheet'!I65-'Data Sheet'!I60 -> 111024.81 | H69: ='Data Sheet'!J65-'Data Sheet'!J60 -> 128615.12 | I69: ='Data Sheet'!K65-'Data Sheet'!K60 -> 132231.74
B70: Total Assets | C70: ='Data Sheet'!E66 -> 306687.09 | D70: ='Data Sheet'!F66 -> 310095.05 | E70: ='Data Sheet'!G66 -> 319027.91 | F70: ='Data Sheet'!H66 -> 329721.88 | G70: ='Data Sheet'!I66 -> 339602.34 | H70: ='Data Sheet'!J66 -> 379114.09 | I70: ='Data Sheet'!K66 -> 452382.77
B71: Working Capital/Total Assets(A) | C71: =C69/C70 -> 0.46589812 | D71: =D69/D70 -> 0.40649236 | E71: =E69/E70 -> 0.38970258 | F71: =F69/F70 -> 0.36234025 | G71: =G69/G70 -> 0.32692593 | H71: =H69/H70 -> 0.33925175 | I71: =I69/I70 -> 0.29230057
B73: Retained Earnings/Total Assets
C74: =C68 -> 43921 | D74: =D68 -> 44286 | E74: =E68 -> 44651 | F74: =F68 -> 45016 | G74: =G68 -> 45382 | H74: =H68 -> 45747 | I74: =I68 -> 46112
B75: Retained Earnings | C75: =HistoricalFS!F36*HistoricalFS!F38*HistoricalFS!F44 -> 5279.83 | D75: =HistoricalFS!G36*HistoricalFS!G38*HistoricalFS!G44 -> 0 | E75: =HistoricalFS!H36*HistoricalFS!H38*HistoricalFS!H44 -> 4835.93 | F75: =HistoricalFS!I36*HistoricalFS!I38*HistoricalFS!I44 -> 6360.97 | G75: =HistoricalFS!J36*HistoricalFS!J38*HistoricalFS!J44 -> 5942.42 | H75: =HistoricalFS!K36*HistoricalFS!K38*HistoricalFS!K44 -> 9813.86 | I75: =HistoricalFS!L36*HistoricalFS!L38*HistoricalFS!L44 -> 8946.13
B76: =B70 -> Total Assets | C76: =C$70 -> 306687.09 | D76: =D$70 -> 310095.05 | E76: =E$70 -> 319027.91 | F76: =F$70 -> 329721.88 | G76: =G$70 -> 339602.34 | H76: =H$70 -> 379114.09 | I76: =I$70 -> 452382.77
B77: Retained Earnings/Total Assets(B) | C77: =C75/C76 -> 0.01721569 | D77: =D75/D76 -> 0 | E77: =E75/E76 -> 0.015158329 | F77: =F75/F76 -> 0.019291926 | G77: =G75/G76 -> 0.017498172 | H77: =H75/H76 -> 0.025886297 | I77: =I75/I76 -> 0.019775576
B79: EBIT/Total Assets
C80: =C74 -> 43921 | D80: =D74 -> 44286 | E80: =E74 -> 44651 | F80: =F74 -> 45016 | G80: =G74 -> 45382 | H80: =H74 -> 45747 | I80: =I74 -> 46112
B81: EBIT | C81: =HistoricalFS!F18-HistoricalFS!F24 -> 22090.83 | D81: =HistoricalFS!G18-HistoricalFS!G24 -> 20556.03 | E81: =HistoricalFS!H18-HistoricalFS!H24 -> 21365.94 | F81: =HistoricalFS!I18-HistoricalFS!I24 -> 23663.77 | G81: =HistoricalFS!J18-HistoricalFS!J24 -> 25075.79 | H81: =HistoricalFS!K18-HistoricalFS!K24 -> 30305.72 | I81: =HistoricalFS!L18-HistoricalFS!L24 -> 31045.95
B82: =B76 -> Total Assets | C82: =C76 -> 306687.09 | D82: =D76 -> 310095.05 | E82: =E76 -> 319027.91 | F82: =F76 -> 329721.88 | G82: =G76 -> 339602.34 | H82: =H76 -> 379114.09 | I82: =I76 -> 452382.77
B83: EBIT/Total Assets(C) | C83: =C81/C82 -> 0.072030518 | D83: =D81/D82 -> 0.066289449 | E83: =E81/E82 -> 0.066972009 | F83: =F81/F82 -> 0.07176888 | G83: =G81/G82 -> 0.073838684 | H83: =H81/H82 -> 0.079938258 | I83: =I81/I82 -> 0.068627614
B85: Market cap/Long Term Liabilities
C86: =C80 -> 43921 | D86: =D80 -> 44286 | E86: =E80 -> 44651 | F86: =F80 -> 45016 | G86: =G80 -> 45382 | H86: =H80 -> 45747 | I86: =I80 -> 46112
B87: Market Cap | C87: =('Data Sheet'!E70*'Data Sheet'!E90)/10000000 -> 113504.67 | D87: =('Data Sheet'!F70*'Data Sheet'!F90)/10000000 -> 199292.35 | E87: =('Data Sheet'!G70*'Data Sheet'!G90)/10000000 -> 248359.97 | F87: =('Data Sheet'!H70*'Data Sheet'!H90)/10000000 -> 304174.46 | G87: =('Data Sheet'!I70*'Data Sheet'!I90)/10000000 -> 517411.52 | H87: =('Data Sheet'!J70*'Data Sheet'!J90)/10000000 -> 480258.36 | I87: =('Data Sheet'!K70*'Data Sheet'!K90)/10000000 -> 482035.28
B88: Long Term Liability | C88: ='Data Sheet'!E59 -> 143173.67 | D88: ='Data Sheet'!F59 -> 134629.08 | E88: ='Data Sheet'!G59 -> 125508.08 | F88: ='Data Sheet'!H59 -> 120650.44 | G88: ='Data Sheet'!I59 -> 116322.22 | H88: ='Data Sheet'!J59 -> 132408.92 | I88: ='Data Sheet'!K59 -> 125496.59
B89: Market cap/Long Term Liabilities(D) | C89: =C87/C88 -> 0.79277614 | D89: =D87/D88 -> 1.4803069 | E89: =E87/E88 -> 1.9788365 | F89: =F87/F88 -> 2.5211218 | G89: =G87/G88 -> 4.4480884 | H89: =H87/H88 -> 3.6270846 | I89: =I87/I88 -> 3.8410229
B93: Sales/Total Assets
C94: =C86 -> 43921 | D94: =D86 -> 44286 | E94: =E86 -> 44651 | F94: =F86 -> 45016 | G94: =G86 -> 45382 | H94: =H86 -> 45747 | I94: =I86 -> 46112
B95: Sales | C95: ='Data Sheet'!E17 -> 145452.36 | D95: ='Data Sheet'!F17 -> 135979.03 | E95: ='Data Sheet'!G17 -> 156521.23 | F95: ='Data Sheet'!H17 -> 183340.7 | G95: ='Data Sheet'!I17 -> 221112.91 | H95: ='Data Sheet'!J17 -> 255734.45 | I95: ='Data Sheet'!K17 -> 285874.36
B96: Total Assets | C96: =C82 -> 306687.09 | D96: =D82 -> 310095.05 | E96: =E82 -> 319027.91 | F96: =F82 -> 329721.88 | G96: =G82 -> 339602.34 | H96: =H82 -> 379114.09 | I96: =I82 -> 452382.77
B97: Sales/Total Assets(E) | C97: =C95/C96 -> 0.47426959 | D97: =D95/D96 -> 0.43850758 | E97: =E95/E96 -> 0.49061924 | F97: =F95/F96 -> 0.55604651 | G97: =G95/G96 -> 0.6510936 | H97: =H95/H96 -> 0.67455802 | I97: =I95/I96 -> 0.63193026
B99: Altman's Z Score
C100: =C94 -> 43921 | D100: =D94 -> 44286 | E100: =E94 -> 44651 | F100: =F94 -> 45016 | G100: =G94 -> 45382 | H100: =H94 -> 45747 | I100: =I94 -> 46112
B101: Final Score | C101: =(C71*1.2)+(C77*1.4)+(C83*3.3)+(C89*0.6)+(C97*1) -> 1.7708157 | D101: =(D71*1.2)+(D77*1.4)+(D83*3.3)+(D89*0.6)+(D97*1) -> 2.0332377 | E101: =(E71*1.2)+(E77*1.4)+(E83*3.3)+(E89*0.6)+(E97*1) -> 2.3877935 | F101: =(F71*1.2)+(F77*1.4)+(F83*3.3)+(F89*0.6)+(F97*1) -> 2.7673739 | G101: =(G71*1.2)+(G77*1.4)+(G83*3.3)+(G89*0.6)+(G97*1) -> 3.9804229 | H101: =(H71*1.2)+(H77*1.4)+(H83*3.3)+(H89*0.6)+(H97*1) -> 3.557948 | I101: =(I71*1.2)+(I77*1.4)+(I83*3.3)+(I89*0.6)+(I97*1) -> 3.5414616
B102: Financial Stability | C102: =IF(C101<1.81,"Distressed",IF(C101>3,"Strong","Grey Zone")) -> Distressed | D102: =IF(D101<1.81,"Distressed",IF(D101>3,"Strong","Grey Zone")) -> Grey Zone | E102: =IF(E101<1.81,"Distressed",IF(E101>3,"Strong","Grey Zone")) -> Grey Zone | F102: =IF(F101<1.81,"Distressed",IF(F101>3,"Strong","Grey Zone")) -> Grey Zone | G102: =IF(G101<1.81,"Distressed",IF(G101>3,"Strong","Grey Zone")) -> Strong | H102: =IF(H101<1.81,"Distressed",IF(H101>3,"Strong","Grey Zone")) -> Strong | I102: =IF(I101<1.81,"Distressed",IF(I101>3,"Strong","Grey Zone")) -> Strong

Sheet DCF>
B2: Calculation of PV of FCFF | E2: ='Intrisic Growth'!I2 -> 46082 | F2: =E2+365 -> 46447 | G2: =F2+365 -> 46812 | H2: =G2+366 -> 47178 | I2: =H2+365 -> 47543 | J2: =I2+365 -> 47908
B4: EBIT | E4: =_xlfn.IFERROR('Data Sheet'!K34-'Data Sheet'!K26,0) -> 32956.34 | F4: =E4*(1+$D$14) -> 39794.781 | G4: =F4*(1+$D$14) -> 48052.198 | H4: =G4*(1+$D$14) -> 58023.028 | I4: =H4*(1+$D$14) -> 70062.807 | J4: =I4*(1+$D$14) -> 84600.839
B5: Tax Rate | E5: 0.25 | F5: =$E$5 -> 0.25 | G5: =$E$5 -> 0.25 | H5: =$E$5 -> 0.25 | I5: =$E$5 -> 0.25 | J5: =$E$5 -> 0.25
B6: EBIT(1-Tax) | E6: =E4*(1-E5) -> 24717.255 | F6: =E6*(1+$D$14) -> 29846.085 | G6: =F6*(1+$D$14) -> 36039.148 | H6: =G6*(1+$D$14) -> 43517.271 | I6: =H6*(1+$D$14) -> 52547.105 | J6: =I6*(1+$D$14) -> 63450.63
B7: Less: Reinvestment Rate | E7: 0.31
B8: Free Cash Flow to Firm(FCFF) | E8: =E6*(1-E7) -> 17054.906 | F8: =E8*(1+$D$14) -> 20593.799 | G8: =F8*(1+$D$14) -> 24867.012 | H8: =G8*(1+$D$14) -> 30026.917 | I8: =H8*(1+$D$14) -> 36257.503 | J8: =I8*(1+$D$14) -> 43780.934
B9: Mid Year Convention | F9: 0.5 | G9: =F9+1 -> 1.5 | H9: =G9+1 -> 2.5 | I9: =H9+1 -> 3.5 | J9: =I9+1 -> 4.5
B10: Discounting Factor | F10: =1/(1+$D$16)^F9 -> 0.944059 | G10: =1/(1+$D$16)^G9 -> 0.84139012 | H10: =1/(1+$D$16)^H9 -> 0.74988676 | I10: =1/(1+$D$16)^I9 -> 0.66833462 | J10: =1/(1+$D$16)^J9 -> 0.59565149
B12: PV of FCFF | F12: =F8*F10 -> 19441.761 | G12: =G8*G10 -> 20922.859 | H12: =H8*H10 -> 22516.788 | I12: =I8*I10 -> 24232.144 | J12: =J8*J10 -> 26078.179
B14: Expected Growth | D14: 0.2075
B15: Terminal Growth | D15: 0.045 | F15: Sensitivity Analysis
B16: WACC | D16: =WACC!J43 -> 0.12202291 | F16: =D37 -> 3203.2351 | G16: 0.12 | H16: 0.122 | I16: 0.135 | J16: 0.14
F17: 0.03 | G17: 2774.6041 | H17: 2719.2986 | I17: 2411.1678 | J17: 2312.0488
B18: Calculation of Terminal Value | F18: 0.04 | G18: 3092.6109 | H18: 3022.8045 | I18: 2640.7065 | J18: 2520.1987
F19: 0.045 | G19: 3283.4149 | H19: 3204.1197 | I19: 2774.6041 | J19: 2640.7065
B20: FCFF(n+1) | D20: =J8*(1+D14) -> 52865.478 | F20: 0.05 | G20: 3501.4767 | H20: 3410.6176 | I20: 2924.2543 | J20: 2774.6041
B21: WACC | D21: =D16 -> 0.12202291 | F21: 0.06 | G21: 4046.6311 | H21: 3923.5318 | I21: 3283.4149 | J21: 3092.6109
B22: Terminal Growth Rate | D22: =D15 -> 0.045 | F22: 0.07 | G22: 4809.8474 | H22: 4633.7206 | I22: 3753.0864 | J22: 3501.4767
B24: Terminal Value | D24: =D20/(D21-D22) -> 686360.4
B26: Calculation of Enterprise Value
B28: PV of FCFF | D28: =SUM(F12:J12) -> 113191.73
B29: PV Terminal Value | D29: =D24*J10 -> 408831.59
B30: Value of Operating Activities | D30: =SUM(D28:D29) -> 522023.32
B32: Add: Cash | D32: ='Data Sheet'!K69 -> 20847.67
B33: Less: debt | D33: =SUM('Raw FS'!N7:N9) -> 102332
B34: Value of Equity | D34: =D30+D32-D33 -> 440538.99
B35: NO. of Shares | D35: ='Data Sheet'!B6 -> 137.5294
B37: Equity Value Per Share | D37: =D34/D35 -> 3203.2351
B39: Share Price | D39: ='Data Sheet'!B8 -> 3785.6
B40: Discount/Premium | D40: =D39/D37-1 -> 0.18180524

Sheet WACC
B2: Weighted Average Cost of Capital
B4: All figures are in INR unless stated otherwise.
B6: Peer Comps
G7: Debt/ | H7: Debt/ | I7: Levered | J7: Unlevered
B8: Name | C8: Country | D8: Total Debt | E8: Total Equity | F8: Tax Rate 1 | G8: Equity | H8: Capital | I8: Beta 2 | J8: Beta 3
B10: ='Beta - Comps'!C4 -> Larsen & Tourbo | C10: India | D10: ='Relative Data'!G3 -> 102332 | E10: ='Beta - Comps'!E4 -> 520631.29 | F10: 0.25 | G10: =D10/E10 -> 0.19655369 | H10: =D10/(D10+E10) -> 0.1642665 | I10: ='Beta - Regression'!J13 -> 1.1623457 | J10: =I10/(1+(1-F10)*G10) -> 1.0130122
B11: ='Beta - Comps'!C5 -> Rail Vikas | C11: India | D11: ='Relative Data'!G4 -> 4818.49 | E11: ='Beta - Comps'!E5 -> 47163.14 | F11: =$F$10 -> 0.25 | G11: =D11/E11 -> 0.10216644 | H11: =D11/(D11+E11) -> 0.092696016 | I11: 1.94 | J11: =I11/(1+(1-F11)*G11) -> 1.8019276
B12: ='Beta - Comps'!C6 -> NBCC | C12: India | D12: ='Relative Data'!G5 -> 0.26 | E12: ='Beta - Comps'!E6 -> 25717.5 | F12: =$F$10 -> 0.25 | G12: =D12/E12 -> 1.0109847e-05 | H12: =D12/(D12+E12) -> 1.0109745e-05 | I12: 1.94 | J12: =I12/(1+(1-F12)*G12) -> 1.9399853
B13: ='Beta - Comps'!C7 -> IRB Infra.Devl. | C13: India | D13: ='Relative Data'!G6 -> 20027.06 | E13: ='Beta - Comps'!E7 -> 23757.42 | F13: =$F$10 -> 0.25 | G13: =D13/E13 -> 0.84298127 | H13: =D13/(D13+E13) -> 0.45740089 | I13: 1.09 | J13: =I13/(1+(1-F13)*G13) -> 0.66779561
B14: ='Beta - Comps'!C8 -> Cemindia Project | C14: India | D14: ='Relative Data'!G7 -> 1001.23 | E14: ='Beta - Comps'!E8 -> 23519.42 | F14: =$F$10 -> 0.25 | G14: =D14/E14 -> 0.042570353 | H14: =D14/(D14+E14) -> 0.040832115 | I14: 1.46 | J14: =I14/(1+(1-F14)*G14) -> 1.4148277
E16: Average | F16: =AVERAGE(F10:F14) -> 0.25 | G16: =AVERAGE(G10:G14) -> 0.23685637 | H16: =AVERAGE(H10:H14) -> 0.15104113 | I16: =AVERAGE(I10:I14) -> 1.5184691 | J16: =AVERAGE(J10:J14) -> 1.3675097
E17: Median | F17: =MEDIAN(F10:F14) -> 0.25 | G17: =MEDIAN(G10:G14) -> 0.10216644 | H17: =MEDIAN(H10:H14) -> 0.092696016 | I17: =MEDIAN(I10:I14) -> 1.46 | J17: =MEDIAN(J10:J14) -> 1.4148277
B20: Cost of Debt | G20: Cost of Equity
B22: Pre-tax Cost of Debt | E22: 0.076 | G22: Risk Free Rate | J22: 0.0685
B23: Tax Rate | E23: =F17 -> 0.25 | G23: Equity Risk Premium | J23: =Rm!G11-WACC!J22 -> 0.056
B24: After Tax Cost of Debt | E24: =E22*(1-E23) -> 0.057 | G24: Levered Beta 4 | J24: ='Beta - Regression'!J13 -> 1.1623457
G25: Cost of Equity | J25: =J22+(J23*J24) -> 0.13359136
B28: Capital Structure | G28: Levered Beta
D30: Current | E30: Target | G30: Comps Median Unlevered Beta | J30: =J17 -> 1.4148277
B31: Total Debt | C31: =D10 -> 102332 | D31: =C31/$C$33 -> 0.1642665 | E31: =H16 -> 0.15104113 | G31: Target Debt/ Equity | J31: =E35 -> 0.17791336
B32: Market Capitalization | C32: =E10 -> 520631.29 | D32: =C32/$C$33 -> 0.8357335 | E32: =E33-E31 -> 0.84895887 | G32: Tax Rate | J32: =E23 -> 0.25
B33: Total Capitalization | C33: =SUM(C31:C32) -> 622963.29 | D33: =C33/$C$33 -> 1 | E33: =D33 -> 1 | G33: Levered Beta | J33: =J30*(1+(1-J31)*J32) -> 1.7056055
B35: Debt / Equity | D35: =D31/D32 -> 0.19655369 | E35: =E31/E32 -> 0.17791336 | G35: Weighted Average Cost of Capital
B37: 1. Tax Rate considered as Marginal Tax Rate for the country | G37: Cost of Equity | J37: =J25 -> 0.13359136
B38: 2. Levered Beta is based on 5 year monthly data | G38: Equity Weight | J38: =E32 -> 0.84895887
B39: 3. Unlevered Beta = Levered Beta/(1+(1-Tax Rate) x Debt/Equity)
B40: 4. Levered Beta = Unlevered Beta/(1+(1-Tax Rate) x Debt/Equity) | G40: Cost of Debt | J40: =E24 -> 0.057
B41: 5.All Beta are calculated on 5 year monthly basis | G41: Debt Weight | J41: =E31 -> 0.15104113
G43: WACC | J43: =(J37*J38)+(J40*J41) -> 0.12202291

Sheet Intrisic Growth
A2: # | B2: Calculation of ROIC | E2: ='Raw FS'!J$2 -> 44621 | F2: ='Raw FS'!K$2 -> 44986 | G2: ='Raw FS'!L$2 -> 45352 | H2: ='Raw FS'!M$2 -> 45717 | I2: ='Raw FS'!N$2 -> 46082
B4: Current Assets
B5: ='Raw FS'!B39 -> Inventories | E5: ='Raw FS'!J39 -> 5943 | F5: ='Raw FS'!K39 -> 6829 | G5: ='Raw FS'!L39 -> 6620 | H5: ='Raw FS'!M39 -> 7671 | I5: ='Raw FS'!N39 -> 9531
B6: ='Raw FS'!B40 -> Trade receivables + | E6: ='Raw FS'!J40 -> 46139 | F6: ='Raw FS'!K40 -> 44732 | G6: ='Raw FS'!L40 -> 48771 | H6: ='Raw FS'!M40 -> 53714 | I6: ='Raw FS'!N40 -> 60461
B7: ='Raw FS'!B42 -> Loans n Advances | E7: ='Raw FS'!J42 -> 41799 | F7: ='Raw FS'!K42 -> 40356 | G7: ='Raw FS'!L42 -> 34700 | H7: ='Raw FS'!M42 -> 34244 | I7: ='Raw FS'!N42 -> 40747
B8: ='Raw FS'!B43 -> Other asset items | E8: ='Raw FS'!J43 -> 122604 | F8: ='Raw FS'!K43 -> 124781 | G8: ='Raw FS'!L43 -> 142496 | H8: ='Raw FS'!M43 -> 159071 | I8: ='Raw FS'!N43 -> 218241
B9: Total Current Assets | E9: =SUM(E5:E8) -> 216485 | F9: =SUM(F5:F8) -> 216698 | G9: =SUM(G5:G8) -> 232587 | H9: =SUM(H5:H8) -> 254700 | I9: =SUM(I5:I8) -> 328980
B11: Current Liabilities
B12: ='Raw FS'!B14 -> Trade Payables | E12: ='Raw FS'!J14 -> 51366 | F12: ='Raw FS'!K14 -> 49784 | G12: ='Raw FS'!L14 -> 53293 | H12: ='Raw FS'!M14 -> 52459 | I12: ='Raw FS'!N14 -> 69456
B13: ='Raw FS'!B15 -> Advance from Customers | E13: ='Raw FS'!J15 -> 17963 | F13: ='Raw FS'!K15 -> 20425 | G13: ='Raw FS'!L15 -> 26875 | H13: ='Raw FS'!M15 -> 29087 | I13: ='Raw FS'!N15 -> 39586
B14: ='Raw FS'!B16 -> Other liability items | E14: ='Raw FS'!J16 -> 28817 | F14: ='Raw FS'!K16 -> 35297 | G14: ='Raw FS'!L16 -> 40562 | H14: ='Raw FS'!M16 -> 49755 | I14: ='Raw FS'!N16 -> 89312
B15: Total Current Liabilities | E15: =SUM(E12:E14) -> 98146 | F15: =SUM(F12:F14) -> 105506 | G15: =SUM(G12:G14) -> 120730 | H15: =SUM(H12:H14) -> 131301 | I15: =SUM(I12:I14) -> 198354
A17: # | B17: Net Working Capital | E17: =E9-E15 -> 118339 | F17: =F9-F15 -> 111192 | G17: =G9-G15 -> 111857 | H17: =H9-H15 -> 123399 | I17: =I9-I15 -> 130626
B19: Non Current Assets
B20: ='Raw FS'!B20 -> Land | E20: ='Raw FS'!J20 -> 1347 | F20: ='Raw FS'!K20 -> 1436 | G20: ='Raw FS'!L20 -> 1000 | H20: ='Raw FS'!M20 -> 1703 | I20: ='Raw FS'!N20 -> 1803
B21: ='Raw FS'!B21 -> Building | E21: ='Raw FS'!J21 -> 6745 | F21: ='Raw FS'!K21 -> 6998 | G21: ='Raw FS'!L21 -> 6680 | H21: ='Raw FS'!M21 -> 9951 | I21: ='Raw FS'!N21 -> 11326
B22: ='Raw FS'!B22 -> Plant Machinery | E22: ='Raw FS'!J22 -> 9298 | F22: ='Raw FS'!K22 -> 10859 | G22: ='Raw FS'!L22 -> 12570 | H22: ='Raw FS'!M22 -> 14870 | I22: ='Raw FS'!N22 -> 15800
B23: ='Raw FS'!B23 -> Ships Vessels | E23: ='Raw FS'!J23 -> 947 | F23: ='Raw FS'!K23 -> 969 | G23: ='Raw FS'!L23 -> 1007 | H23: ='Raw FS'!M23 -> 1025 | I23: ='Raw FS'!N23 -> 1696
B24: ='Raw FS'!B24 -> Equipments | E24: ='Raw FS'!J24 -> 630 | F24: ='Raw FS'!K24 -> 716 | G24: ='Raw FS'!L24 -> 762 | H24: ='Raw FS'!M24 -> 871 | I24: ='Raw FS'!N24 -> 1060
B25: ='Raw FS'!B25 -> Computers | E25: ='Raw FS'!J25 -> 2067 | F25: ='Raw FS'!K25 -> 2448 | G25: ='Raw FS'!L25 -> 2572 | H25: ='Raw FS'!M25 -> 2803 | I25: ='Raw FS'!N25 -> 3152
B26: ='Raw FS'!B26 -> Furniture n fittings | E26: ='Raw FS'!J26 -> 499 | F26: ='Raw FS'!K26 -> 508 | G26: ='Raw FS'!L26 -> 633 | H26: ='Raw FS'!M26 -> 672 | I26: ='Raw FS'!N26 -> 754
B27: ='Raw FS'!B27 -> Railway sidings | E27: ='Raw FS'!J27 -> 0 | F27: ='Raw FS'!K27 -> 0 | G27: ='Raw FS'!L27 -> 0 | H27: ='Raw FS'!M27 -> 0 | I27: ='Raw FS'!N27 -> 0
B28: ='Raw FS'!B28 -> Vehicles | E28: ='Raw FS'!J28 -> 650 | F28: ='Raw FS'!K28 -> 652 | G28: ='Raw FS'!L28 -> 657 | H28: ='Raw FS'!M28 -> 768 | I28: ='Raw FS'!N28 -> 1380
B29: ='Raw FS'!B29 -> Intangible Assets | E29: ='Raw FS'!J29 -> 24950 | F29: ='Raw FS'!K29 -> 25099 | G29: ='Raw FS'!L29 -> 24837 | H29: ='Raw FS'!M29 -> 25860 | I29: ='Raw FS'!N29 -> 9432
B30: ='Raw FS'!B30 -> Other fixed assets | E30: ='Raw FS'!J30 -> 9361 | F30: ='Raw FS'!K30 -> 9071 | G30: ='Raw FS'!L30 -> 10408 | H30: ='Raw FS'!M30 -> 7867 | I30: ='Raw FS'!N30 -> 7487
B32: Gross Block | E32: =SUM(E20:E31) -> 56494 | F32: =SUM(F20:F31) -> 58756 | G32: =SUM(G20:G31) -> 61126 | H32: =SUM(H20:H31) -> 66390 | I32: =SUM(I20:I31) -> 53890
B33: ='Raw FS'!B32 -> Accumulated Depreciation | E33: =-('Raw FS'!J32) -> -13550 | F33: =-('Raw FS'!K32) -> -16115 | G33: =-('Raw FS'!L32) -> -18161 | H33: =-('Raw FS'!M32) -> -22334 | I33: =-('Raw FS'!N32) -> -23023
A34: # | B34: Net Non Current Assets | E34: =SUM(E32:E33) -> 42944 | F34: =SUM(F32:F33) -> 42641 | G34: =SUM(G32:G33) -> 42965 | H34: =SUM(H32:H33) -> 44056 | I34: =SUM(I32:I33) -> 30867
A36: # | B36: Invested Capital | E36: =E34+E17 -> 161283 | F36: =F34+F17 -> 153833 | G36: =G34+G17 -> 154822 | H36: =H34+H17 -> 167455 | I36: =I34+I17 -> 161493
B37: EBIT | E37: =(HistoricalFS!H27+HistoricalFS!H21) -> 21365.94 | F37: =(HistoricalFS!I27+HistoricalFS!I21) -> 23663.77 | G37: =(HistoricalFS!J27+HistoricalFS!J21) -> 25075.79 | H37: =(HistoricalFS!K27+HistoricalFS!K21) -> 30305.72 | I37: =(HistoricalFS!L27+HistoricalFS!L21) -> 31045.95
A39: # | B39: ROIC | E39: =E37/E36 -> 0.13247484 | F39: =F37/F36 -> 0.15382766 | G39: =G37/G36 -> 0.16196529 | H39: =H37/H36 -> 0.18097829 | I39: =I37/I36 -> 0.19224332
A42: # | B42: Calculation of Reinvestment Rate | E42: ='Raw FS'!J$2 -> 44621 | F42: ='Raw FS'!K$2 -> 44986 | G42: ='Raw FS'!L$2 -> 45352 | H42: ='Raw FS'!M$2 -> 45717 | I42: ='Raw FS'!N$2 -> 46082
B44: Net Capex | E44: =-SUM(CFS!I12:I13) -> 3040 | F44: =-SUM(CFS!J12:J13) -> 3794 | G44: =-SUM(CFS!K12:K13) -> 4211 | H44: =-SUM(CFS!L12:L13) -> 3541 | I44: =-SUM(CFS!M12:M13) -> 4468
B45: Change in Working Capital | F45: =F17-E17 -> -7147 | G45: =G17-F17 -> 665 | H45: =H17-G17 -> 11542 | I45: =I17-H17 -> 7227
B47: EBIT | E47: =E37 -> 21365.94 | F47: =F37 -> 23663.77 | G47: =G37 -> 25075.79 | H47: =H37 -> 30305.72 | I47: =I37 -> 31045.95
B48: Marginal Tax Rate | E48: ='Data Sheet'!G32 -> 0.29002613 | F48: ='Data Sheet'!H32 -> 0.26209318 | G48: ='Data Sheet'!I32 -> 0.24113484 | H48: ='Data Sheet'!J32 -> 0.24986015 | I48: ='Data Sheet'!K32 -> 0.26241376
B49: EBIT(1-T) | E49: =E47*(1-E48) -> 15169.259 | F49: =F47*(1-F48) -> 17461.657 | G49: =G47*(1-G48) -> 19029.143 | H49: =H47*(1-H48) -> 22733.528 | I49: =I47*(1-I48) -> 22899.065
B51: Reinvestment | F51: =SUM(F44:F45) -> -3353 | G51: =SUM(G44:G45) -> 4876 | H51: =SUM(H44:H45) -> 15083 | I51: =SUM(I44:I45) -> 11695
B53: Reinvestment Rate | F53: =F51/F49 -> -0.19202072 | G53: =G51/G49 -> 0.25623854 | H53: =H51/H49 -> 0.66346938 | I53: =I51/I49 -> 0.51071953
H55: 4 Year Average | I55: =AVERAGE(F53:I53) -> 0.30960169
H56: 4 Year Median | I56: =MEDIAN(F53:I53) -> 0.38347904
A58: # | B58: Calculation of Growth Rate | E58: ='Raw FS'!J$2 -> 44621 | F58: ='Raw FS'!K$2 -> 44986 | G58: ='Raw FS'!L$2 -> 45352 | H58: ='Raw FS'!M$2 -> 45717 | I58: ='Raw FS'!N$2 -> 46082
B60: Reinvestment Rate | F60: =F53 -> -0.19202072 | G60: =G53 -> 0.25623854 | H60: =H53 -> 0.66346938 | I60: =I53 -> 0.51071953
B61: ROIC | F61: =F39 -> 0.15382766 | G61: =G39 -> 0.16196529 | H61: =H39 -> 0.18097829 | I61: =I39 -> 0.19224332
B63: Intrinsic Growth | F63: =F60*F61 -> -0.029538097 | G63: =G60*G61 -> 0.04150175 | H63: =H60*H61 -> 0.12007356 | I63: =I60*I61 -> 0.098182417
H65: 4 Year Average | I65: =AVERAGE(F63:I63) -> 0.057554906
H66: 4 Year Median | I66: =MEDIAN(F63:I63) -> 0.069842083

Sheet Beta - Regression
E2: needs correction
B3: Regression Beta - 5 Years Monthly
B5: ='Data Sheet'!B1&" - "&"Weekly Returns" -> LARSEN & TOUBRO LTD - Weekly Returns | F5: NIFTY Returns | I5: Beta Drifting | L5: Beta 1 | M5: =SLOPE(D8:D66,G8:G66) -> 1.2164609
B6: Date | C6: Closing Price | D6: Return | F6: Closing Price | G6: Return | L6: Beta 2 | M6: =_xlfn.COVARIANCE.S(D7:D66,G7:G66)/VAR(G7:G66) -> 1.2164609
B7: 46029 | C7: 3937.7 | F7: 23979.6 | I7: Levered Raw Beta | J7: =M5 -> 1.2164609
B8: 46028 | C8: 4143.4 | D8: =C8/C7-1 -> 0.052238616 | F8: 23865.75 | G8: =F8/F7-1 -> -0.0047477856 | I8: Raw Beta Weight | J8: 0.75
B9: 46027 | C9: 4076.5 | D9: =C9/C8-1 -> -0.01614616 | F9: 23547.75 | G9: =F9/F8-1 -> -0.013324534
B10: 46026 | C10: 4014 | D10: =C10/C9-1 -> -0.01533178 | F10: 23997.55 | G10: =F10/F9-1 -> 0.019101613 | I10: Market Beta | J10: 1
B11: 46025 | C11: 3504.1 | D11: =C11/C10-1 -> -0.12703039 | F11: 22331.4 | G11: =F11/F10-1 -> -0.069430004 | I11: Market Beta Weight | J11: 0.25
B12: 46024 | C12: 4278.3 | D12: =C12/C11-1 -> 0.22094118 | F12: 25178.65 | G12: =F12/F11-1 -> 0.12749984
B13: 46023 | C13: 3932.3 | D13: =C13/C12-1 -> -0.080873244 | F13: 25320.65 | G13: =F13/F12-1 -> 0.0056396987 | I13: Adjusted Beta | J13: =(J7*J8)+(J10*J11) -> 1.1623457
B14: 45669 | C14: 4083.5 | D14: =C14/C13-1 -> 0.038450779 | F14: 26129.6 | G14: =F14/F13-1 -> 0.031948232
B15: 45668 | C15: 4069.6 | D15: =C15/C14-1 -> -0.0034039427 | F15: 26202.95 | G15: =F15/F14-1 -> 0.0028071612
B16: 45667 | C16: 4030.9 | D16: =C16/C15-1 -> -0.0095095341 | F16: 25722.1 | G16: =F16/F15-1 -> -0.018350987
B17: 45666 | C17: 3659 | D17: =C17/C16-1 -> -0.092262274 | F17: 24611.1 | G17: =F17/F16-1 -> -0.04319243
B18: 45665 | C18: 3601 | D18: =C18/C17-1 -> -0.015851325 | F18: 24426.85 | G18: =F18/F17-1 -> -0.0074864594
B19: 45664 | C19: 3636.5 | D19: =C19/C18-1 -> 0.0098583727 | F19: 24768.35 | G19: =F19/F18-1 -> 0.013980517
B20: 45663 | C20: 3669.8 | D20: =C20/C19-1 -> 0.0091571566 | F20: 25517.05 | G20: =F20/F19-1 -> 0.030228094
B21: 45662 | C21: 3675.1 | D21: =C21/C20-1 -> 0.0014442204 | F21: 24750.7 | G21: =F21/F20-1 -> -0.03003286
B22: 45661 | C22: 3341 | D22: =C22/C21-1 -> -0.090909091 | F22: 24334.2 | G22: =F22/F21-1 -> -0.016827807
B23: 45660 | C23: 3492.3 | D23: =C23/C22-1 -> 0.045285843 | F23: 23519.35 | G23: =F23/F22-1 -> -0.033485794
B24: 45659 | C24: 3163.85 | D24: =C24/C23-1 -> -0.094049767 | F24: 22124.7 | G24: =F24/F23-1 -> -0.059297982
B25: 45658 | C25: 3567.4 | D25: =C25/C24-1 -> 0.12755029 | F25: 23508.4 | G25: =F25/F24-1 -> 0.062540961
... B66: 44204 | C66: 1668.44 | D66: =C66/C65-1 -> -0.018056406 | F66: 17132.2 | G66: =F66/F65-1 -> -0.027582351

Sheet Relative valuation
B3: Amount in crores
B4: Comparable Company Valuations
D6: Market Data | K6: Financials | O6: Valuation
B7: Company | C7: Ticker | D7: Share prize | E7: Shares Outstanding | F7: Equity Value | G7: Net Debt | H7: Enterprise Value | K7: Revenue | L7: EBITDA | M7: Net Income | O7: EV/Revenue | P7: EV/EBITDA | Q7: P/E
B9: ='Beta - Comps'!C4 -> Larsen & Tourbo | D9: ='Relative Data'!D3 -> 3785.6 | E9: ='Relative Data'!E3 -> 137.5294 | F9: =E9*D9 -> 520631.29 | G9: ='Relative Data'!I3 -> 81484.33 | H9: =G9+F9 -> 602115.62 | K9: ='Data Sheet'!K17 -> 285874.36 | L9: ='Relative Data'!L3 -> 37321.09 | M9: ='Relative Data'!M3 -> 16083.99 | O9: ='Relative Data'!J3/'Relative Data'!K3 -> 2.1062246 | P9: ='Relative Data'!$J3/'Relative valuation'!L9 -> 16.133388 | Q9: ='Relative Data'!O3 -> 32.369536
B10: ='Beta - Comps'!C5 -> Rail Vikas | D10: ='Beta - Comps'!D5 -> 226.2 | E10: ='Relative Data'!E4 -> 208.50195 | F10: =E10*D10 -> 47163.14 | G10: ='Relative Data'!I4 -> 3850.24 | H10: =G10+F10 -> 51013.38 | K10: ='Relative Data'!K4 -> 20412.12 | L10: ='Relative Data'!L4 -> 1636.6179 | M10: ='Relative Data'!M4 -> 875.01187 | O10: ='Relative Data'!$J4/'Relative valuation'!K10 -> 2.4991711 | P10: ='Relative Data'!$J4/'Relative valuation'!L10 -> 31.17 | Q10: ='Relative Data'!O4 -> 53.9
B11: ='Beta - Comps'!C6 -> NBCC | D11: ='Beta - Comps'!D6 -> 95.25 | E11: ='Relative Data'!E5 -> 270 | F11: =E11*D11 -> 25717.5 | G11: ='Relative Data'!I5 -> -6515.36 | H11: =G11+F11 -> 19202.14 | K11: ='Relative Data'!K5 -> 12888.61 | L11: ='Relative Data'!L5 -> 924.06833 | M11: ='Relative Data'!M5 -> 661.96911 | O11: ='Relative Data'!$J5/'Relative valuation'!K11 -> 1.4898534 | P11: ='Relative Data'!$J5/'Relative valuation'!L11 -> 20.78 | Q11: ='Relative Data'!O5 -> 38.85
B12: ='Beta - Comps'!C7 -> IRB Infra.Devl. | D12: ='Beta - Comps'!D7 -> 19.67 | E12: ='Relative Data'!E6 -> 1207.7997 | F12: =E12*D12 -> 23757.42 | G12: ='Relative Data'!I6 -> 18116.1 | H12: =G12+F12 -> 41873.52 | K12: ='Relative Data'!K6 -> 7648.15 | L12: ='Relative Data'!L6 -> 2476.2578 | M12: ='Relative Data'!M6 -> 879.25315 | O12: ='Relative Data'!$J6/'Relative valuation'!K12 -> 5.4749868 | P12: ='Relative Data'!$J6/'Relative valuation'!L12 -> 16.91 | Q12: ='Relative Data'!O6 -> 27.02
B13: ='Beta - Comps'!C8 -> Cemindia Project | D13: ='Beta - Comps'!D8 -> 1369.1 | E13: ='Relative Data'!E7 -> 17.178745 | F13: =E13*D13 -> 23519.42 | G13: ='Relative Data'!I7 -> 52.38 | H13: =G13+F13 -> 23571.8 | K13: ='Relative Data'!K7 -> 10060.58 | L13: ='Relative Data'!L7 -> 1393.9562 | M13: ='Relative Data'!M7 -> 588.42682 | O13: ='Relative Data'!$J7/'Relative valuation'!K13 -> 2.3429862 | P13: ='Relative Data'!$J7/'Relative valuation'!L13 -> 16.91 | Q13: ='Relative Data'!O7 -> 39.97
B15: High | O15: =MAX(O9:O13) -> 5.4749868 | P15: =MAX(P9:P13) -> 31.17 | Q15: =MAX(Q9:Q13) -> 53.9
B16: 75th Percentile | O16: =QUARTILE(O9:O13,3) -> 2.4991711 | P16: =QUARTILE(P9:P13,3) -> 20.78 | Q16: =QUARTILE(Q9:Q13,3) -> 39.97
B17: Average | O17: =AVERAGE(O9:O13) -> 2.7826444 | P17: =AVERAGE(P9:P13) -> 20.380678 | Q17: =AVERAGE(Q9:Q13) -> 38.421907
B18: Median | O18: =MEDIAN(O9:O13) -> 2.3429862 | P18: =MEDIAN(P9:P13) -> 16.91 | Q18: =MEDIAN(Q9:Q13) -> 38.85
B19: 25th Percentile | O19: =QUARTILE(O9:O13,1) -> 2.1062246 | P19: =QUARTILE(P9:P13,1) -> 16.91 | Q19: =QUARTILE(Q9:Q13,1) -> 32.369536
B20: Low | O20: =MIN(O9:O13) -> 1.4898534 | P20: =MIN(P9:P13) -> 16.133388 | Q20: =MIN(Q9:Q13) -> 27.02
B22: Comparable Company Valuations | O22: EV/Revenue | P22: EV/EBITDA | Q22: P/E
B24: Implied Enterprise Value | O24: =O18*K9 -> 669799.68 | P24: =P18*L9 -> 631099.63 | Q24: =Q26+Q25 -> 706347.34
B25: Net Debt | O25: =$G$9 -> 81484.33 | P25: =$G$9 -> 81484.33 | Q25: =$G$9 -> 81484.33
B26: Implied Market Value | O26: =O24-O25 -> 588315.35 | P26: =P24-P25 -> 549615.3 | Q26: =Q18*M9 -> 624863.01
B27: Shares Outstanding | O27: =$E$9 -> 137.5294 | P27: =$E$9 -> 137.5294 | Q27: =$E$9 -> 137.5294
B29: Implied value per share | O29: =O26/O27 -> 4277.7425 | P29: =P26/P27 -> 3996.3478 | Q29: =Q26/Q27 -> 4543.4868
B31: Source: The Valuation School, Screener.in
O32: =IF(O29>$D$8,"Undervalued","Overvalued") -> Undervalued | P32: =IF(P29>$D$8,"Undervalued","Overvalued") -> Undervalued | Q32: =IF(Q29>$D$8,"Undervalued","Overvalued") -> Undervalued

Sheet Beta - Comps
B3: S.No. | C3: Name | D3: CMP Rs. | E3: Mar Cap Rs.Cr. | F3: Debt Rs.Cr. | G3: Debt / Eq
B4: 1 | C4: ='Relative Data'!C3 -> Larsen & Tourbo | D4: ='Relative Data'!D3 -> 3785.6 | E4: ='Relative Data'!F3 -> 520631.29 | F4: ='Relative Data'!G3 -> 102332 | G4: ='Beta - Comps'!F4/'Beta - Comps'!E4 -> 0.19655369
B5: 2 | C5: ='Relative Data'!C4 -> Rail Vikas | D5: ='Relative Data'!D4 -> 226.2 | E5: ='Relative Data'!F4 -> 47163.14 | F5: ='Relative Data'!G4 -> 4818.49 | G5: ='Beta - Comps'!F5/'Beta - Comps'!E5 -> 0.10216644
B6: 3 | C6: ='Relative Data'!C5 -> NBCC | D6: ='Relative Data'!D5 -> 95.25 | E6: ='Relative Data'!F5 -> 25717.5 | F6: ='Relative Data'!G5 -> 0.26 | G6: ='Beta - Comps'!F6/'Beta - Comps'!E6 -> 1.0109847e-05
B7: 4 | C7: ='Relative Data'!C6 -> IRB Infra.Devl. | D7: ='Relative Data'!D6 -> 19.67 | E7: ='Relative Data'!F6 -> 23757.42 | F7: ='Relative Data'!G6 -> 20027.06 | G7: ='Beta - Comps'!F7/'Beta - Comps'!E7 -> 0.84298127
B8: 5 | C8: ='Relative Data'!C7 -> Cemindia Project | D8: ='Relative Data'!D7 -> 1369.1 | E8: ='Relative Data'!F7 -> 23519.42 | F8: ='Relative Data'!G7 -> 1001.23 | G8: ='Beta - Comps'!F8/'Beta - Comps'!E8 -> 0.042570353

Sheet Rm
B6: Return on Markets - Nifty 50
B8: Year | C8: Annual
B9: 2011 | C9: -0.2462 | E9: Average Return | G9: =AVERAGE(C9:C23) -> 0.1106
B10: 2012 | C10: 0.277 | E10: Dividend Yield | G10: 0.0139
B11: 2013 | C11: 0.0676 | E11: Total Market Returns | G11: =SUM(G10,G9) -> 0.1245
B12: 2014 | C12: 0.3139
B13: 2015 | C13: -0.0406
B14: 2016 | C14: 0.0301
B15: 2017 | C15: 0.2865
B16: 2018 | C16: 0.0315
B17: 2019 | C17: 0.1202
B18: 2020 | C18: 0.1417
B19: 2021 | C19: 0.2412
B20: 2022 | C20: 0.0432
B21: 2023 | C21: 0.2003
B22: 2024 | C22: 0.0876
B23: 2025 | C23: 0.105

Sheet Analysis
B3: ='Data Sheet'!B1 -> LARSEN & TOUBRO LTD
B4: =CONCATENATE("(",_xlfn.XLOOKUP(B3,'List Of Stocks'!B2:B5442,'List Of Stocks'!D2:D5442)," | ","BSE Code: ",_xlfn.XLOOKUP(Analysis!B3,'List Of Stocks'!B2:B5442,'List Of Stocks'!C2:C5442, ,0)," ) ") -> (LT | BSE Code: 500510 )
B5: =CONCATENATE("INR"," ",'Data Sheet'!B8) -> INR 3785.6
B6: ="52 Week"&" "&"("&"High -"&" INR "&'Football Field Analysis'!Q10&" "&"LOW - "&" INR "&'Football Field Analysis'!N10&")" -> 52 Week (High - INR 4440 LOW - INR 3288)
B8: About The Company
B9: Larsen & Toubro Limited (L&T) is an Indian multinational conglomerate headquartered in Mumbai. It operates in sectors including industrial technology, heavy industry, engineering, construction, manufacturing, power, information technology, defence, and financial services. L&T was founded in 1938 in Bombay by Danish engineers Henning Holck-Larsen and Søren Kristian Toubro. As of 31 March 2022, the L&T Group consisted of 93 subsidiaries, 5 associate companies, 27 joint ventures, and 35 joint operations. As of 1 October 2023, S N Subrahmanyan serves as the chairman and managing director of L&T, having succeeded A M Naik.
B17: Financial Summary
B68: Return On Equity(ROE)
C69: =HistoricalFS!F3 -> 43921 | D69: =HistoricalFS!G3 -> 44286 | E69: =HistoricalFS!H3 -> 44651 | F69: =HistoricalFS!I3 -> 45016 | G69: =HistoricalFS!J3 -> 45382 | H69: =HistoricalFS!K3 -> 45747 | I69: =HistoricalFS!L3 -> 46112
B70: Net Profit | C70: =_xlfn.IFERROR('Data Sheet'!E30,0) -> 9549.03 | D70: =_xlfn.IFERROR('Data Sheet'!F30,0) -> 11582.93 | E70: =_xlfn.IFERROR('Data Sheet'!G30,0) -> 8669.33 | F70: =_xlfn.IFERROR('Data Sheet'!H30,0) -> 10470.72 | G70: =_xlfn.IFERROR('Data Sheet'!I30,0) -> 13059.11 | H70: =_xlfn.IFERROR('Data Sheet'!J30,0) -> 15037.11 | I70: =_xlfn.IFERROR('Data Sheet'!K30,0) -> 16083.99
B71: Average Shareholder Equity | C71: =_xlfn.IFERROR((('Data Sheet'!E57+'Data Sheet'!E58)+('Data Sheet'!D58+'Data Sheet'!D57))/2,0) -> 64549.01 | D71: =_xlfn.IFERROR((('Data Sheet'!F57+'Data Sheet'!F58)+('Data Sheet'!E58+'Data Sheet'!E57))/2,0) -> 71295.875 | E71: =_xlfn.IFERROR((('Data Sheet'!G57+'Data Sheet'!G58)+('Data Sheet'!F58+'Data Sheet'!F57))/2,0) -> 79138.095 | F71: =_xlfn.IFERROR((('Data Sheet'!H57+'Data Sheet'!H58)+('Data Sheet'!G58+'Data Sheet'!G57))/2,0) -> 85866.805 | G71: =_xlfn.IFERROR((('Data Sheet'!I57+'Data Sheet'!I58)+('Data Sheet'!H58+'Data Sheet'!H57))/2,0) -> 87842.595 | H71: =_xlfn.IFERROR((('Data Sheet'!J57+'Data Sheet'!J58)+('Data Sheet'!I58+'Data Sheet'!I57))/2,0) -> 92007.42 | I71: =_xlfn.IFERROR((('Data Sheet'!K57+'Data Sheet'!K58)+('Data Sheet'!J58+'Data Sheet'!J57))/2,0) -> 103472.7
B72: Return On Equity | C72: =C70/C71 -> 0.14793457 | D72: =D70/D71 -> 0.16246284 | E72: =E70/E71 -> 0.10954686 | F72: =F70/F71 -> 0.12194142 | G72: =G70/G71 -> 0.14866489 | H72: =H70/H71 -> 0.16343367 | I72: =I70/I71 -> 0.15544187
B74: ROE - Dupont Equation
C75: =C69 -> 43921 | D75: =D69 -> 44286 | E75: =E69 -> 44651 | F75: =F69 -> 45016 | G75: =G69 -> 45382 | H75: =H69 -> 45747 | I75: =I69 -> 46112
B76: =B70 -> Net Profit | C76: =C70 -> 9549.03 | D76: =D70 -> 11582.93 | E76: =E70 -> 8669.33 | F76: =F70 -> 10470.72 | G76: =G70 -> 13059.11 | H76: =H70 -> 15037.11 | I76: =I70 -> 16083.99
B77: Revenue | C77: =_xlfn.IFERROR('Data Sheet'!E17,0) -> 145452.36 | D77: =_xlfn.IFERROR('Data Sheet'!F17,0) -> 135979.03 | E77: =_xlfn.IFERROR('Data Sheet'!G17,0) -> 156521.23 | F77: =_xlfn.IFERROR('Data Sheet'!H17,0) -> 183340.7 | G77: =_xlfn.IFERROR('Data Sheet'!I17,0) -> 221112.91 | H77: =_xlfn.IFERROR('Data Sheet'!J17,0) -> 255734.45 | I77: =_xlfn.IFERROR('Data Sheet'!K17,0) -> 285874.36
B78: Net Profit Margin(A) | C78: =C76/C77 -> 0.065650568 | D78: =D76/D77 -> 0.085181737 | E78: =E76/E77 -> 0.055387566 | F78: =F76/F77 -> 0.057110723 | G78: =G76/G77 -> 0.059060821 | H78: =H76/H77 -> 0.058799704 | I78: =I76/I77 -> 0.056262443
C80: =C75 -> 43921 | D80: =D75 -> 44286 | E80: =E75 -> 44651 | F80: =F75 -> 45016 | G80: =G75 -> 45382 | H80: =H75 -> 45747 | I80: =I75 -> 46112
B81: Revenue | C81: =C77 -> 145452.36 | D81: =D77 -> 135979.03 | E81: =E77 -> 156521.23 | F81: =F77 -> 183340.7 | G81: =G77 -> 221112.91 | H81: =H77 -> 255734.45 | I81: =I77 -> 285874.36
B82: Average Total Assets | C82: =_xlfn.IFERROR(('Data Sheet'!E66+'Data Sheet'!D66)/2,0) -> 292361.66 | D82: =_xlfn.IFERROR(('Data Sheet'!F66+'Data Sheet'!E66)/2,0) -> 308391.07 | E82: =_xlfn.IFERROR(('Data Sheet'!G66+'Data Sheet'!F66)/2,0) -> 314561.48 | F82: =_xlfn.IFERROR(('Data Sheet'!H66+'Data Sheet'!G66)/2,0) -> 324374.9 | G82: =_xlfn.IFERROR(('Data Sheet'!I66+'Data Sheet'!H66)/2,0) -> 334662.11 | H82: =_xlfn.IFERROR(('Data Sheet'!J66+'Data Sheet'!I66)/2,0) -> 359358.22 | I82: =_xlfn.IFERROR(('Data Sheet'!K66+'Data Sheet'!J66)/2,0) -> 415748.43
B83: Asset Turnover Ratio(B) | C83: =C81/C82 -> 0.49750833 | D83: =D81/D82 -> 0.4409305 | E83: =E81/E82 -> 0.4975855 | F83: =F81/F82 -> 0.56521236 | G83: =G81/G82 -> 0.66070494 | H83: =H81/H82 -> 0.71164214 | I83: =I81/I82 -> 0.68761381
C85: =C80 -> 43921 | D85: =D80 -> 44286 | E85: =E80 -> 44651 | F85: =F80 -> 45016 | G85: =G80 -> 45382 | H85: =H80 -> 45747 | I85: =I80 -> 46112
B86: Average Total Assets | C86: =_xlfn.IFERROR(('Data Sheet'!E66+'Data Sheet'!D66)/2,0) -> 292361.66 | D86: =_xlfn.IFERROR(('Data Sheet'!F66+'Data Sheet'!E66)/2,0) -> 308391.07 | E86: =_xlfn.IFERROR(('Data Sheet'!G66+'Data Sheet'!F66)/2,0) -> 314561.48 | F86: =_xlfn.IFERROR(('Data Sheet'!H66+'Data Sheet'!G66)/2,0) -> 324374.9 | G86: =_xlfn.IFERROR(('Data Sheet'!I66+'Data Sheet'!H66)/2,0) -> 334662.11 | H86: =_xlfn.IFERROR(('Data Sheet'!J66+'Data Sheet'!I66)/2,0) -> 359358.22 | I86: =_xlfn.IFERROR(('Data Sheet'!K66+'Data Sheet'!J66)/2,0) -> 415748.43
B87: Average Shareholder Equity | C87: =_xlfn.IFERROR((('Data Sheet'!E57+'Data Sheet'!E58)+('Data Sheet'!D58+'Data Sheet'!D57))/2,0) -> 64549.01 | D87: =_xlfn.IFERROR((('Data Sheet'!F57+'Data Sheet'!F58)+('Data Sheet'!E58+'Data Sheet'!E57))/2,0) -> 71295.875 | E87: =_xlfn.IFERROR((('Data Sheet'!G57+'Data Sheet'!G58)+('Data Sheet'!F58+'Data Sheet'!F57))/2,0) -> 79138.095 | F87: =_xlfn.IFERROR((('Data Sheet'!H57+'Data Sheet'!H58)+('Data Sheet'!G58+'Data Sheet'!G57))/2,0) -> 85866.805 | G87: =_xlfn.IFERROR((('Data Sheet'!I57+'Data Sheet'!I58)+('Data Sheet'!H58+'Data Sheet'!H57))/2,0) -> 87842.595 | H87: =_xlfn.IFERROR((('Data Sheet'!J57+'Data Sheet'!J58)+('Data Sheet'!I58+'Data Sheet'!I57))/2,0) -> 92007.42 | I87: =_xlfn.IFERROR((('Data Sheet'!K57+'Data Sheet'!K58)+('Data Sheet'!J58+'Data Sheet'!J57))/2,0) -> 103472.7
B88: Financial Leverage(C) | C88: =C86/C87 -> 4.5292974 | D88: =D86/D87 -> 4.3255107 | E88: =E86/E87 -> 3.9748427 | F88: =F86/F87 -> 3.7776519 | G88: =G86/G87 -> 3.8097931 | H88: =H86/H87 -> 3.9057525 | I88: =I86/I87 -> 4.0179529
B90: Return On Equity(A*B*C) | C90: =C88*C83*C78 -> 0.14793457 | D90: =D88*D83*D78 -> 0.16246284 | E90: =E88*E83*E78 -> 0.10954686 | F90: =F88*F83*F78 -> 0.12194142 | G90: =G88*G83*G78 -> 0.14866489 | H90: =H88*H83*H78 -> 0.16343367 | I90: =I88*I83*I78 -> 0.15544187
B92: Return On Asset(ROA)
C93: =C85 -> 43921 | D93: =D85 -> 44286 | E93: =E85 -> 44651 | F93: =F85 -> 45016 | G93: =G85 -> 45382 | H93: =H85 -> 45747 | I93: =I85 -> 46112
B94: Net Profit | C94: =C76 -> 9549.03 | D94: =D76 -> 11582.93 | E94: =E76 -> 8669.33 | F94: =F76 -> 10470.72 | G94: =G76 -> 13059.11 | H94: =H76 -> 15037.11 | I94: =I76 -> 16083.99
B95: =B86 -> Average Total Assets | C95: =C86 -> 292361.66 | D95: =D86 -> 308391.07 | E95: =E86 -> 314561.48 | F95: =F86 -> 324374.9 | G95: =G86 -> 334662.11 | H95: =H86 -> 359358.22 | I95: =I86 -> 415748.43
B96: Return On Asset | C96: =C94/C95 -> 0.032661704 | D96: =D94/D95 -> 0.037559226 | E96: =E94/E95 -> 0.02756005 | F96: =F94/F95 -> 0.032279687 | G96: =G94/G95 -> 0.039021776 | H96: =H94/H95 -> 0.041844347 | I96: =I94/I95 -> 0.038686833
B98: ROA - Dupont Analysis
C99: =C93 -> 43921 | D99: =D93 -> 44286 | E99: =E93 -> 44651 | F99: =F93 -> 45016 | G99: =G93 -> 45382 | H99: =H93 -> 45747 | I99: =I93 -> 46112
B100: Net Profit | C100: =C94 -> 9549.03 | D100: =D94 -> 11582.93 | E100: =E94 -> 8669.33 | F100: =F94 -> 10470.72 | G100: =G94 -> 13059.11 | H100: =H94 -> 15037.11 | I100: =I94 -> 16083.99
B101: Revenue | C101: =C81 -> 145452.36 | D101: =D81 -> 135979.03 | E101: =E81 -> 156521.23 | F101: =F81 -> 183340.7 | G101: =G81 -> 221112.91 | H101: =H81 -> 255734.45 | I101: =I81 -> 285874.36
B102: Net Profit Margin(A) | C102: =C100/C101 -> 0.065650568 | D102: =D100/D101 -> 0.085181737 | E102: =E100/E101 -> 0.055387566 | F102: =F100/F101 -> 0.057110723 | G102: =G100/G101 -> 0.059060821 | H102: =H100/H101 -> 0.058799704 | I102: =I100/I101 -> 0.056262443
C104: =C99 -> 43921 | D104: =D99 -> 44286 | E104: =E99 -> 44651 | F104: =F99 -> 45016 | G104: =G99 -> 45382 | H104: =H99 -> 45747 | I104: =I99 -> 46112
B105: Revenue | C105: =C101 -> 145452.36 | D105: =D101 -> 135979.03 | E105: =E101 -> 156521.23 | F105: =F101 -> 183340.7 | G105: =G101 -> 221112.91 | H105: =H101 -> 255734.45 | I105: =I101 -> 285874.36
B106: Average Total Assets | C106: =C86 -> 292361.66 | D106: =D86 -> 308391.07 | E106: =E86 -> 314561.48 | F106: =F86 -> 324374.9 | G106: =G86 -> 334662.11 | H106: =H86 -> 359358.22 | I106: =I86 -> 415748.43
B107: Asset Turnover Ratio(B) | C107: =C105/C106 -> 0.49750833 | D107: =D105/D106 -> 0.4409305 | E107: =E105/E106 -> 0.4975855 | F107: =F105/F106 -> 0.56521236 | G107: =G105/G106 -> 0.66070494 | H107: =H105/H106 -> 0.71164214 | I107: =I105/I106 -> 0.68761381
B109: Return On Asset(A*B) | C109: =C107*C102 -> 0.032661704 | D109: =D107*D102 -> 0.037559226 | E109: =E107*E102 -> 0.02756005 | F109: =F107*F102 -> 0.032279687 | G109: =G107*G102 -> 0.039021776 | H109: =H107*H102 -> 0.041844347 | I109: =I107*I102 -> 0.038686833

Sheet HistoricalFS
B2: ="Historical Financial Statement - "&'Data Sheet'!B1 -> Historical Financial Statement - LARSEN & TOUBRO LTD
B3: Years | C3: ='Data Sheet'!B16 -> 42825 | D3: ='Data Sheet'!C16 -> 43190 | E3: ='Data Sheet'!D16 -> 43555 | F3: ='Data Sheet'!E16 -> 43921 | G3: ='Data Sheet'!F16 -> 44286 | H3: ='Data Sheet'!G16 -> 44651 | I3: ='Data Sheet'!H16 -> 45016 | J3: ='Data Sheet'!I16 -> 45382 | ... L3: ='Data Sheet'!K16 -> 46112 | M3: LTM
A5: # | B5: Income Statement
B6: Sales | C6: =_xlfn.IFERROR('Data Sheet'!B17,0) -> 109311.81 | D6: =_xlfn.IFERROR('Data Sheet'!C17,0) -> 119683.16 | E6: =_xlfn.IFERROR('Data Sheet'!D17,0) -> 135220.29 | F6: =_xlfn.IFERROR('Data Sheet'!E17,0) -> 145452.36 | G6: =_xlfn.IFERROR('Data Sheet'!F17,0) -> 135979.03 | H6: =_xlfn.IFERROR('Data Sheet'!G17,0) -> 156521.23 | I6: =_xlfn.IFERROR('Data Sheet'!H17,0) -> 183340.7 | J6: =_xlfn.IFERROR('Data Sheet'!I17,0) -> 221112.91 | ... L6: =_xlfn.IFERROR('Data Sheet'!K17,0) -> 285874.36 | M6: =_xlfn.IFERROR(SUM('Data Sheet'!H42:K42),0) -> 285874.31
B7: Sales Growth | C7: - | D7: =D6/C6-1 -> 0.094878586 | E7: =E6/D6-1 -> 0.12981885 | F7: =F6/E6-1 -> 0.075669635 | G7: =G6/F6-1 -> -0.065130122 | H7: =H6/G6-1 -> 0.15106888 | I7: =I6/H6-1 -> 0.17134717 | J7: =J6/I6-1 -> 0.20602196 | K7: =K6/J6-1 -> 0.15657856 | ... M7: =M6/L6-1 -> -1.7490201e-07
B9: COGS | C9: =_xlfn.IFERROR(SUM('Data Sheet'!B18,'Data Sheet'!B20:B22)-1*'Data Sheet'!B19,0) -> 84990.29 | D9: =_xlfn.IFERROR(SUM('Data Sheet'!C18,'Data Sheet'!C20:C22)-1*'Data Sheet'!C19,0) -> 91701.74 | E9: =_xlfn.IFERROR(SUM('Data Sheet'!D18,'Data Sheet'!D20:D22)-1*'Data Sheet'!D19,0) -> 104612.44 | F9: =_xlfn.IFERROR(SUM('Data Sheet'!E18,'Data Sheet'!E20:E22)-1*'Data Sheet'!E19,0) -> 111501.59 | G9: =_xlfn.IFERROR(SUM('Data Sheet'!F18,'Data Sheet'!F20:F22)-1*'Data Sheet'!F19,0) -> 103742.91 | H9: =_xlfn.IFERROR(SUM('Data Sheet'!G18,'Data Sheet'!G20:G22)-1*'Data Sheet'!G19,0) -> 123562.17 | I9: =_xlfn.IFERROR(SUM('Data Sheet'!H18,'Data Sheet'!H20:H22)-1*'Data Sheet'!H19,0) -> 147655.94 | J9: =_xlfn.IFERROR(SUM('Data Sheet'!I18,'Data Sheet'!I20:I22)-1*'Data Sheet'!I19,0) -> 181664.96 | ... L9: =_xlfn.IFERROR(SUM('Data Sheet'!K18,'Data Sheet'!K20:K22)-1*'Data Sheet'!K19,0) -> 237751.87 | M9: =_xlfn.IFERROR(SUM('Data Sheet'!H43:K43),0) -> 249727.83
B10: COGS % Sales | C10: =C9/C6 -> 0.77750327 | D10: =D9/D6 -> 0.7662042 | E10: =E9/E6 -> 0.77364455 | F10: =F9/F6 -> 0.76658495 | G10: =G9/G6 -> 0.76293315 | H10: =H9/H6 -> 0.78942754 | I10: =I9/I6 -> 0.80536368 | J10: =J9/J6 -> 0.82159364 | ... M10: =M9/M6 -> 0.87355814
B12: Gross Profit | C12: =C6-C9 -> 24321.52 | D12: =D6-D9 -> 27981.42 | E12: =E6-E9 -> 30607.85 | F12: =F6-F9 -> 33950.77 | G12: =G6-G9 -> 32236.12 | H12: =H6-H9 -> 32959.06 | I12: =I6-I9 -> 35684.76 | J12: =J6-J9 -> 39447.95 | ... M12: =M6-M9 -> 36146.48
B13: Gross Margins | C13: =C12/C6 -> 0.22249673 | D13: =D12/D6 -> 0.2337958 | E13: =E12/E6 -> 0.22635545 | F13: =F12/F6 -> 0.23341505 | G13: =G12/G6 -> 0.23706685 | H13: =H12/H6 -> 0.21057246 | I13: =I12/I6 -> 0.19463632 | J13: =J12/J6 -> 0.17840636 | ... M13: =M12/M6 -> 0.12644186
B15: Selling & General Expenses | C15: =_xlfn.IFERROR(SUM('Data Sheet'!B23:B24),0) -> 7701.11 | D15: =_xlfn.IFERROR(SUM('Data Sheet'!C23:C24),0) -> 7870.08 | E15: =_xlfn.IFERROR(SUM('Data Sheet'!D23:D24),0) -> 7742.03 | F15: =_xlfn.IFERROR(SUM('Data Sheet'!E23:E24),0) -> 9397.67 | G15: =_xlfn.IFERROR(SUM('Data Sheet'!F23:F24),0) -> 8775.88 | H15: =_xlfn.IFERROR(SUM('Data Sheet'!G23:G24),0) -> 8645.17 | I15: =_xlfn.IFERROR(SUM('Data Sheet'!H23:H24),0) -> 8518.74 | J15: =_xlfn.IFERROR(SUM('Data Sheet'!I23:I24),0) -> 10689.83 | ... L15: =_xlfn.IFERROR(SUM('Data Sheet'!K23:K24),0) -> 12711.79
B16: S&G Exp % Sales | C16: =C15/C6 -> 0.070450851 | D16: =D15/D6 -> 0.065757622 | E16: =E15/E6 -> 0.057254943 | F16: =F15/F6 -> 0.064609952 | G16: =G15/G6 -> 0.064538481 | H16: =H15/H6 -> 0.05523321 | I16: =I15/I6 -> 0.046463988 | J16: =J15/J6 -> 0.048345572 | ... M16: =M15/M6 -> 0
B18: EBITDA | C18: =C12-C15 -> 16620.41 | D18: =D12-D15 -> 20111.34 | E18: =E12-E15 -> 22865.82 | F18: =F12-F15 -> 24553.1 | G18: =G12-G15 -> 23460.24 | H18: =H12-H15 -> 24313.89 | I18: =I12-I15 -> 27166.02 | J18: =J12-J15 -> 28758.12 | ... L18: =L12-L15 -> 35410.7 | M18: =_xlfn.IFERROR(SUM('Data Sheet'!H51:K51),0) -> 37109.3
B19: EBITDA Margins | C19: =C18/C6 -> 0.15204588 | D19: =D18/D6 -> 0.16803818 | E19: =E18/E6 -> 0.16910051 | F19: =F18/F6 -> 0.1688051 | G19: =G18/G6 -> 0.17252837 | H19: =H18/H6 -> 0.15533925 | I19: =I18/I6 -> 0.14817234 | J19: =J18/J6 -> 0.13006079 | ... M19: =M18/M6 -> 0.12980985
B21: Interest | C21: =_xlfn.IFERROR('Data Sheet'!B27,0) -> 6828.66 | D21: =_xlfn.IFERROR('Data Sheet'!C27,0) -> 7713.63 | E21: =_xlfn.IFERROR('Data Sheet'!D27,0) -> 9338.73 | F21: =_xlfn.IFERROR('Data Sheet'!E27,0) -> 11020.78 | G21: =_xlfn.IFERROR('Data Sheet'!F27,0) -> 11749.58 | H21: =_xlfn.IFERROR('Data Sheet'!G27,0) -> 9234.98 | I21: =_xlfn.IFERROR('Data Sheet'!H27,0) -> 9445.44 | J21: =_xlfn.IFERROR('Data Sheet'!I27,0) -> 9512.17 | ... L21: =_xlfn.IFERROR('Data Sheet'!K27,0) -> 10055.94 | M21: =_xlfn.IFERROR(SUM('Data Sheet'!H46:K46),0) -> 9844.16
B22: Interest % Sales | C22: =C21/C6 -> 0.062469554 | D22: =D21/D6 -> 0.064450421 | E22: =E21/E6 -> 0.069063082 | F22: =F21/F6 -> 0.075769001 | G22: =G21/G6 -> 0.086407294 | H22: =H21/H6 -> 0.059001453 | I22: =I21/I6 -> 0.051518512 | J22: =J21/J6 -> 0.043019514 | ... M22: =M21/M6 -> 0.034435273
B24: Depreciation | C24: =_xlfn.IFERROR('Data Sheet'!B26,0) -> 2369.93 | D24: =_xlfn.IFERROR('Data Sheet'!C26,0) -> 2223.48 | E24: =_xlfn.IFERROR('Data Sheet'!D26,0) -> 1923.03 | F24: =_xlfn.IFERROR('Data Sheet'!E26,0) -> 2462.27 | G24: =_xlfn.IFERROR('Data Sheet'!F26,0) -> 2904.21 | H24: =_xlfn.IFERROR('Data Sheet'!G26,0) -> 2947.95 | I24: =_xlfn.IFERROR('Data Sheet'!H26,0) -> 3502.25 | J24: =_xlfn.IFERROR('Data Sheet'!I26,0) -> 3682.33 | ... L24: =_xlfn.IFERROR('Data Sheet'!K26,0) -> 4364.75 | M24: =_xlfn.IFERROR(SUM('Data Sheet'!H45:K45),0) -> 4364.76
B25: Depreciation%Sales | C25: =C24/C6 -> 0.021680457 | D25: =D24/D6 -> 0.018578052 | E25: =E24/E6 -> 0.01422146 | F25: =F24/F6 -> 0.016928361 | G25: =G24/G6 -> 0.021357778 | H25: =H24/H6 -> 0.018834186 | I25: =I24/I6 -> 0.019102414 | J25: =J24/J6 -> 0.016653618 | ... M25: =M24/M6 -> 0.015268109
B27: Earnings Before Tax | C27: =_xlfn.IFERROR(C18-SUM(C24,C21),0) -> 7421.82 | D27: =_xlfn.IFERROR(D18-SUM(D24,D21),0) -> 10174.23 | E27: =_xlfn.IFERROR(E18-SUM(E24,E21),0) -> 11604.06 | F27: =_xlfn.IFERROR(F18-SUM(F24,F21),0) -> 11070.05 | G27: =_xlfn.IFERROR(G18-SUM(G24,G21),0) -> 8806.45 | H27: =_xlfn.IFERROR(H18-SUM(H24,H21),0) -> 12130.96 | I27: =_xlfn.IFERROR(I18-SUM(I24,I21),0) -> 14218.33 | J27: =_xlfn.IFERROR(J18-SUM(J24,J21),0) -> 15563.62 | ... M27: =_xlfn.IFERROR(M18-SUM(M24,M21),0) -> 22900.38
B28: EBT % Sales | C28: =C27/C6 -> 0.067895866 | D28: =D27/D6 -> 0.085009704 | E28: =E27/E6 -> 0.085815967 | F28: =F27/F6 -> 0.076107737 | G28: =G27/G6 -> 0.064763295 | H28: =H27/H6 -> 0.077503608 | I28: =I27/I6 -> 0.077551411 | J28: =J27/J6 -> 0.070387659 | ... M28: =M27/M6 -> 0.080106464
B30: Tax | C30: =_xlfn.IFERROR('Data Sheet'!B29,0) -> 2006.59 | D30: =_xlfn.IFERROR('Data Sheet'!C29,0) -> 3198.87 | E30: =_xlfn.IFERROR('Data Sheet'!D29,0) -> 4067.09 | F30: =_xlfn.IFERROR('Data Sheet'!E29,0) -> 3263.2 | G30: =_xlfn.IFERROR('Data Sheet'!F29,0) -> 4010.82 | H30: =_xlfn.IFERROR('Data Sheet'!G29,0) -> 4203.92 | I30: =_xlfn.IFERROR('Data Sheet'!H29,0) -> 4484.16 | J30: =_xlfn.IFERROR('Data Sheet'!I29,0) -> 4947.39 | ... L30: =_xlfn.IFERROR('Data Sheet'!K29,0) -> 6816.41 | M30: =_xlfn.IFERROR(SUM('Data Sheet'!H48:K48),0) -> 6816.39
B31: Effective Tax Rate | C31: =C30/C27 -> 0.2703636 | D31: =D30/D27 -> 0.31440905 | E31: =E30/E27 -> 0.35048854 | F31: =F30/F27 -> 0.29477735 | G31: =G30/G27 -> 0.45544118 | H31: =H30/H27 -> 0.34654471 | I31: =I30/I27 -> 0.31537881 | J31: =J30/J27 -> 0.3178817 | ... M31: =M30/M27 -> 0.29765401
B33: Net Profit | C33: =_xlfn.IFERROR(C27-C30,0) -> 5415.23 | D33: =_xlfn.IFERROR(D27-D30,0) -> 6975.36 | E33: =_xlfn.IFERROR(E27-E30,0) -> 7536.97 | F33: =_xlfn.IFERROR(F27-F30,0) -> 7806.85 | G33: =_xlfn.IFERROR(G27-G30,0) -> 4795.63 | H33: =_xlfn.IFERROR(H27-H30,0) -> 7927.04 | I33: =_xlfn.IFERROR(I27-I30,0) -> 9734.17 | J33: =_xlfn.IFERROR(J27-J30,0) -> 10616.23 | ... M33: =_xlfn.IFERROR(M27-M30,0) -> 16083.99
B34: Net Margins | C34: =C33/C6 -> 0.049539295 | D34: =D33/D6 -> 0.058281884 | E34: =E33/E6 -> 0.055738455 | F34: =F33/F6 -> 0.0536729 | G34: =G33/G6 -> 0.035267423 | H34: =H33/H6 -> 0.050645143 | I34: =I33/I6 -> 0.053093339 | J34: =J33/J6 -> 0.04801271 | ... M34: =M33/M6 -> 0.056262453
B36: No of Equity Shares | C36: =_xlfn.IFERROR('Data Sheet'!B93,0) -> 139.94 | D36: =_xlfn.IFERROR('Data Sheet'!C93,0) -> 140.14 | E36: =_xlfn.IFERROR('Data Sheet'!D93,0) -> 140.27 | F36: =_xlfn.IFERROR('Data Sheet'!E93,0) -> 140.39 | G36: =_xlfn.IFERROR('Data Sheet'!F93,0) -> 140.46 | H36: =_xlfn.IFERROR('Data Sheet'!G93,0) -> 140.5 | I36: =_xlfn.IFERROR('Data Sheet'!H93,0) -> 140.55 | J36: =_xlfn.IFERROR('Data Sheet'!I93,0) -> 137.47 | ... L36: =_xlfn.IFERROR('Data Sheet'!K93,0) -> 137.56 | M36: =L36 -> 137.56
B38: Earnings per Share | C38: =_xlfn.IFERROR(C33/C36,0) -> 38.696799 | D38: =_xlfn.IFERROR(D33/D36,0) -> 49.774226 | E38: =_xlfn.IFERROR(E33/E36,0) -> 53.731874 | F38: =_xlfn.IFERROR(F33/F36,0) -> 55.608305 | G38: =_xlfn.IFERROR(G33/G36,0) -> 34.142318 | H38: =_xlfn.IFERROR(H33/H36,0) -> 56.420214 | I38: =_xlfn.IFERROR(I33/I36,0) -> 69.257702 | J38: =_xlfn.IFERROR(J33/J36,0) -> 77.225795 | ... M38: =_xlfn.IFERROR(M33/M36,0) -> 116.92345
B39: EPS Growth % | D39: =_xlfn.IFERROR(D38/C38-1,0) -> 0.28626211 | E39: =_xlfn.IFERROR(E38/D38-1,0) -> 0.079512005 | F39: =_xlfn.IFERROR(F38/E38-1,0) -> 0.034922124 | G39: =_xlfn.IFERROR(G38/F38-1,0) -> -0.38602125 | H39: =_xlfn.IFERROR(H38/G38-1,0) -> 0.65250096 | I39: =_xlfn.IFERROR(I38/H38-1,0) -> 0.22753349 | J39: =_xlfn.IFERROR(J38/I38-1,0) -> 0.11504992 | K39: =_xlfn.IFERROR(K38/J38-1,0) -> 0.36435174 | ... M39: =_xlfn.IFERROR(M38/L38-1,0) -> 0.13478509
B41: Dividend per Share | C41: =_xlfn.IFERROR('Data Sheet'!B31/HistoricalFS!C36,0) -> 9.3335001 | D41: =_xlfn.IFERROR('Data Sheet'!C31/HistoricalFS!D36,0) -> 15.999429 | E41: =_xlfn.IFERROR('Data Sheet'!D31/HistoricalFS!E36,0) -> 18.000642 | F41: =_xlfn.IFERROR('Data Sheet'!E31/HistoricalFS!F36,0) -> 18 | G41: =_xlfn.IFERROR('Data Sheet'!F31/HistoricalFS!G36,0) -> 35.998718 | H41: =_xlfn.IFERROR('Data Sheet'!G31/HistoricalFS!H36,0) -> 22.000783 | I41: =_xlfn.IFERROR('Data Sheet'!H31/HistoricalFS!I36,0) -> 24 | J41: =_xlfn.IFERROR('Data Sheet'!I31/HistoricalFS!J36,0) -> 33.998763 | ... M41: =_xlfn.IFERROR('Data Sheet'!L31/HistoricalFS!M36,0) -> 0
B42: Dividend payout ratio | C42: =_xlfn.IFERROR(C41/C38,0) -> 0.24119566 | D42: =_xlfn.IFERROR(D41/D38,0) -> 0.32144004 | E42: =_xlfn.IFERROR(E41/E38,0) -> 0.33500863 | F42: =_xlfn.IFERROR(F41/F38,0) -> 0.32369265 | G42: =_xlfn.IFERROR(G41/G38,0) -> 1.0543724 | H42: =_xlfn.IFERROR(H41/H38,0) -> 0.38994505 | I42: =_xlfn.IFERROR(I41/I38,0) -> 0.34653186 | J42: =_xlfn.IFERROR(J41/J38,0) -> 0.44025139 | ... M42: =_xlfn.IFERROR(M41/M38,0) -> 0
B44: Retained Earnings | C44: =_xlfn.IFERROR(IF(C38>C41,1-C42,0),0) -> 0.75880434 | D44: =_xlfn.IFERROR(IF(D38>D41,1-D42,0),0) -> 0.67855996 | E44: =_xlfn.IFERROR(IF(E38>E41,1-E42,0),0) -> 0.66499137 | F44: =_xlfn.IFERROR(IF(F38>F41,1-F42,0),0) -> 0.67630735 | G44: =_xlfn.IFERROR(IF(G38>G41,1-G42,0),0) -> 0 | H44: =_xlfn.IFERROR(IF(H38>H41,1-H42,0),0) -> 0.61005495 | I44: =_xlfn.IFERROR(IF(I38>I41,1-I42,0),0) -> 0.65346814 | J44: =_xlfn.IFERROR(IF(J38>J41,1-J42,0),0) -> 0.55974861 | ... M44: =_xlfn.IFERROR(IF(M38>M41,1-M42,0),0) -> 1
A46: # | B46: Balance Sheet
B47: Equity Share Capital | C47: =_xlfn.IFERROR('Data Sheet'!B57,0) -> 186.59 | D47: =_xlfn.IFERROR('Data Sheet'!C57,0) -> 280.27 | E47: =_xlfn.IFERROR('Data Sheet'!D57,0) -> 280.55 | F47: =_xlfn.IFERROR('Data Sheet'!E57,0) -> 280.78 | G47: =_xlfn.IFERROR('Data Sheet'!F57,0) -> 280.91 | H47: =_xlfn.IFERROR('Data Sheet'!G57,0) -> 281.01 | I47: =_xlfn.IFERROR('Data Sheet'!H57,0) -> 281.1 | J47: =_xlfn.IFERROR('Data Sheet'!I57,0) -> 274.93 | ... L47: =_xlfn.IFERROR('Data Sheet'!K57,0) -> 275.13
B48: Reserves | C48: =_xlfn.IFERROR('Data Sheet'!B58,0) -> 50029.93 | D48: =_xlfn.IFERROR('Data Sheet'!C58,0) -> 54623.23 | E48: =_xlfn.IFERROR('Data Sheet'!D58,0) -> 62094.25 | F48: =_xlfn.IFERROR('Data Sheet'!E58,0) -> 66442.44 | G48: =_xlfn.IFERROR('Data Sheet'!F58,0) -> 75587.62 | H48: =_xlfn.IFERROR('Data Sheet'!G58,0) -> 82126.65 | I48: =_xlfn.IFERROR('Data Sheet'!H58,0) -> 89044.85 | J48: =_xlfn.IFERROR('Data Sheet'!I58,0) -> 86084.31 | ... L48: =_xlfn.IFERROR('Data Sheet'!K58,0) -> 109014.67
B49: Borrowings | C49: =_xlfn.IFERROR('Data Sheet'!B59,0) -> 93953.95 | D49: =_xlfn.IFERROR('Data Sheet'!C59,0) -> 107524.08 | E49: =_xlfn.IFERROR('Data Sheet'!D59,0) -> 125555.17 | F49: =_xlfn.IFERROR('Data Sheet'!E59,0) -> 143173.67 | G49: =_xlfn.IFERROR('Data Sheet'!F59,0) -> 134629.08 | H49: =_xlfn.IFERROR('Data Sheet'!G59,0) -> 125508.08 | I49: =_xlfn.IFERROR('Data Sheet'!H59,0) -> 120650.44 | J49: =_xlfn.IFERROR('Data Sheet'!I59,0) -> 116322.22 | ... L49: =_xlfn.IFERROR('Data Sheet'!K59,0) -> 125496.59
B50: Other Liabilities | C50: =_xlfn.IFERROR('Data Sheet'!B60,0) -> 67400.18 | D50: =_xlfn.IFERROR('Data Sheet'!C60,0) -> 80811.95 | E50: =_xlfn.IFERROR('Data Sheet'!D60,0) -> 90106.26 | F50: =_xlfn.IFERROR('Data Sheet'!E60,0) -> 96790.2 | G50: =_xlfn.IFERROR('Data Sheet'!F60,0) -> 99597.44 | H50: =_xlfn.IFERROR('Data Sheet'!G60,0) -> 111112.17 | I50: =_xlfn.IFERROR('Data Sheet'!H60,0) -> 119745.49 | J50: =_xlfn.IFERROR('Data Sheet'!I60,0) -> 136920.88 | ... L50: =_xlfn.IFERROR('Data Sheet'!K60,0) -> 217596.38
B51: Total Liabilities | C51: =_xlfn.IFERROR('Data Sheet'!B61,0) -> 211570.65 | D51: =_xlfn.IFERROR('Data Sheet'!C61,0) -> 243239.53 | E51: =_xlfn.IFERROR('Data Sheet'!D61,0) -> 278036.23 | F51: =_xlfn.IFERROR('Data Sheet'!E61,0) -> 306687.09 | G51: =_xlfn.IFERROR('Data Sheet'!F61,0) -> 310095.05 | H51: =_xlfn.IFERROR('Data Sheet'!G61,0) -> 319027.91 | I51: =_xlfn.IFERROR('Data Sheet'!H61,0) -> 329721.88 | J51: =_xlfn.IFERROR('Data Sheet'!I61,0) -> 339602.34 | ... L51: =_xlfn.IFERROR('Data Sheet'!K61,0) -> 452382.77
B53: Fixed Assets Net Block | C53: =_xlfn.IFERROR('Data Sheet'!B62,0) -> 16677.11 | D53: =_xlfn.IFERROR('Data Sheet'!C62,0) -> 18580.19 | E53: =_xlfn.IFERROR('Data Sheet'!D62,0) -> 21193.94 | F53: =_xlfn.IFERROR('Data Sheet'!E62,0) -> 43653.38 | G53: =_xlfn.IFERROR('Data Sheet'!F62,0) -> 44319.32 | H53: =_xlfn.IFERROR('Data Sheet'!G62,0) -> 42945.01 | I53: =_xlfn.IFERROR('Data Sheet'!H62,0) -> 42641 | J53: =_xlfn.IFERROR('Data Sheet'!I62,0) -> 42963.82 | ... L53: =_xlfn.IFERROR('Data Sheet'!K62,0) -> 30866.91
B54: Capital Work in Progress | C54: =_xlfn.IFERROR('Data Sheet'!B63,0) -> 13297.94 | D54: =_xlfn.IFERROR('Data Sheet'!C63,0) -> 13443.43 | E54: =_xlfn.IFERROR('Data Sheet'!D63,0) -> 13919.49 | F54: =_xlfn.IFERROR('Data Sheet'!E63,0) -> 3311.09 | G54: =_xlfn.IFERROR('Data Sheet'!F63,0) -> 500.39 | H54: =_xlfn.IFERROR('Data Sheet'!G63,0) -> 1249.55 | I54: =_xlfn.IFERROR('Data Sheet'!H63,0) -> 3065.57 | J54: =_xlfn.IFERROR('Data Sheet'!I63,0) -> 3045.01 | ... L54: =_xlfn.IFERROR('Data Sheet'!K63,0) -> 3310.95
B55: Investments | C55: =_xlfn.IFERROR('Data Sheet'!B64,0) -> 19753.02 | D55: =_xlfn.IFERROR('Data Sheet'!C64,0) -> 15311.31 | E55: =_xlfn.IFERROR('Data Sheet'!D64,0) -> 20907.1 | F55: =_xlfn.IFERROR('Data Sheet'!E64,0) -> 20047.48 | G55: =_xlfn.IFERROR('Data Sheet'!F64,0) -> 39626.63 | H55: =_xlfn.IFERROR('Data Sheet'!G64,0) -> 39395.18 | I55: =_xlfn.IFERROR('Data Sheet'!H64,0) -> 44798.31 | J55: =_xlfn.IFERROR('Data Sheet'!I64,0) -> 45647.82 | ... L55: =_xlfn.IFERROR('Data Sheet'!K64,0) -> 68376.79
B56: Other Assets | C56: =_xlfn.IFERROR('Data Sheet'!B65-SUM('Data Sheet'!B67:B69),0) -> 123707.91 | D56: =_xlfn.IFERROR('Data Sheet'!C65-SUM('Data Sheet'!C67:C69),0) -> 149907.09 | E56: =_xlfn.IFERROR('Data Sheet'!D65-SUM('Data Sheet'!D67:D69),0) -> 167029.66 | F56: =_xlfn.IFERROR('Data Sheet'!E65-SUM('Data Sheet'!E67:E69),0) -> 178079.19 | G56: =_xlfn.IFERROR('Data Sheet'!F65-SUM('Data Sheet'!F67:F69),0) -> 161356.89 | H56: =_xlfn.IFERROR('Data Sheet'!G65-SUM('Data Sheet'!G67:G69),0) -> 164402.36 | I56: =_xlfn.IFERROR('Data Sheet'!H65-SUM('Data Sheet'!H67:H69),0) -> 165137.09 | J56: =_xlfn.IFERROR('Data Sheet'!I65-SUM('Data Sheet'!I67:I69),0) -> 177196.16 | ... L56: =_xlfn.IFERROR('Data Sheet'!K65-SUM('Data Sheet'!K67:K69),0) -> 258988.26
B57: Total Non Current Assets | C57: =SUM(C53:C56) -> 173435.98 | D57: =SUM(D53:D56) -> 197242.02 | E57: =SUM(E53:E56) -> 223050.19 | F57: =SUM(F53:F56) -> 245091.14 | G57: =SUM(G53:G56) -> 245803.23 | H57: =SUM(H53:H56) -> 247992.1 | I57: =SUM(I53:I56) -> 255641.97 | J57: =SUM(J53:J56) -> 268852.81 | ... L57: =SUM(L53:L56) -> 361542.91
B59: Receivables | C59: =_xlfn.IFERROR('Data Sheet'!B67,0) -> 28688.97 | D59: =_xlfn.IFERROR('Data Sheet'!C67,0) -> 33116.98 | E59: =_xlfn.IFERROR('Data Sheet'!D67,0) -> 36845.87 | F59: =_xlfn.IFERROR('Data Sheet'!E67,0) -> 40731.52 | G59: =_xlfn.IFERROR('Data Sheet'!F67,0) -> 42229.78 | H59: =_xlfn.IFERROR('Data Sheet'!G67,0) -> 46139.32 | I59: =_xlfn.IFERROR('Data Sheet'!H67,0) -> 44731.53 | J59: =_xlfn.IFERROR('Data Sheet'!I67,0) -> 48770.95 | ... L59: =_xlfn.IFERROR('Data Sheet'!K67,0) -> 60461.26
B60: Inventory | C60: =_xlfn.IFERROR('Data Sheet'!B68,0) -> 4139.74 | D60: =_xlfn.IFERROR('Data Sheet'!C68,0) -> 4847.8 | E60: =_xlfn.IFERROR('Data Sheet'!D68,0) -> 6413.93 | F60: =_xlfn.IFERROR('Data Sheet'!E68,0) -> 5746.65 | G60: =_xlfn.IFERROR('Data Sheet'!F68,0) -> 5820.54 | H60: =_xlfn.IFERROR('Data Sheet'!G68,0) -> 5943.32 | I60: =_xlfn.IFERROR('Data Sheet'!H68,0) -> 6828.78 | J60: =_xlfn.IFERROR('Data Sheet'!I68,0) -> 6620.19 | ... L60: =_xlfn.IFERROR('Data Sheet'!K68,0) -> 9530.93
B61: Cash & Bank | C61: =_xlfn.IFERROR('Data Sheet'!B69,0) -> 5305.96 | D61: =_xlfn.IFERROR('Data Sheet'!C69,0) -> 8032.73 | E61: =_xlfn.IFERROR('Data Sheet'!D69,0) -> 11726.24 | F61: =_xlfn.IFERROR('Data Sheet'!E69,0) -> 15117.78 | G61: =_xlfn.IFERROR('Data Sheet'!F69,0) -> 16241.5 | H61: =_xlfn.IFERROR('Data Sheet'!G69,0) -> 18953.17 | I61: =_xlfn.IFERROR('Data Sheet'!H69,0) -> 22519.6 | J61: =_xlfn.IFERROR('Data Sheet'!I69,0) -> 15358.39 | ... L61: =_xlfn.IFERROR('Data Sheet'!K69,0) -> 20847.67
B62: Total Current Assets | C62: =_xlfn.IFERROR(SUM(C59:C61),0) -> 38134.67 | D62: =_xlfn.IFERROR(SUM(D59:D61),0) -> 45997.51 | E62: =_xlfn.IFERROR(SUM(E59:E61),0) -> 54986.04 | F62: =_xlfn.IFERROR(SUM(F59:F61),0) -> 61595.95 | G62: =_xlfn.IFERROR(SUM(G59:G61),0) -> 64291.82 | H62: =_xlfn.IFERROR(SUM(H59:H61),0) -> 71035.81 | I62: =_xlfn.IFERROR(SUM(I59:I61),0) -> 74079.91 | J62: =_xlfn.IFERROR(SUM(J59:J61),0) -> 70749.53 | ... L62: =_xlfn.IFERROR(SUM(L59:L61),0) -> 90839.86
B64: Total Assets | C64: =_xlfn.IFERROR(C62+C57,0) -> 211570.65 | D64: =_xlfn.IFERROR(D62+D57,0) -> 243239.53 | E64: =_xlfn.IFERROR(E62+E57,0) -> 278036.23 | F64: =_xlfn.IFERROR(F62+F57,0) -> 306687.09 | G64: =_xlfn.IFERROR(G62+G57,0) -> 310095.05 | H64: =_xlfn.IFERROR(H62+H57,0) -> 319027.91 | I64: =_xlfn.IFERROR(I62+I57,0) -> 329721.88 | J64: =_xlfn.IFERROR(J62+J57,0) -> 339602.34 | ... L64: =_xlfn.IFERROR(L62+L57,0) -> 452382.77
B66: Check | C66: =C64=C51 -> TRUE | D66: =D64=D51 -> TRUE | E66: =E64=E51 -> TRUE | F66: =F64=F51 -> TRUE | G66: =G64=G51 -> TRUE | H66: =H64=H51 -> TRUE | I66: =I64=I51 -> TRUE | J66: =J64=J51 -> TRUE | ... L66: =L64=L51 -> TRUE
A68: # | B68: Cash Flow Statements
B70: Cash from Operating Activities | C70: ='Data Sheet'!B82 -> 6655.26 | D70: ='Data Sheet'!C82 -> -10031.02 | E70: ='Data Sheet'!D82 -> -4755.83 | F70: ='Data Sheet'!E82 -> 6693.88 | G70: ='Data Sheet'!F82 -> 23073.82 | H70: ='Data Sheet'!G82 -> 19163.58 | I70: ='Data Sheet'!H82 -> 22776.96 | J70: ='Data Sheet'!I82 -> 18266.28 | ... L70: ='Data Sheet'!K82 -> 16740.97
B72: Cash from Investing Activities | C72: ='Data Sheet'!B83 -> -9795.94 | D72: ='Data Sheet'!C83 -> 3914.5 | E72: ='Data Sheet'!D83 -> -11022.8 | F72: ='Data Sheet'!E83 -> -8407.71 | G72: ='Data Sheet'!F83 -> -5750.49 | H72: ='Data Sheet'!G83 -> -3585.38 | I72: ='Data Sheet'!H83 -> -8048.02 | J72: ='Data Sheet'!I83 -> 2178.89 | ... L72: ='Data Sheet'!K83 -> -11380.3
B74: Cash from Financing Activities | C74: ='Data Sheet'!B84 -> 2895.93 | D74: ='Data Sheet'!C84 -> 9370.46 | E74: ='Data Sheet'!D84 -> 15440.17 | F74: ='Data Sheet'!E84 -> 6371.55 | G74: ='Data Sheet'!F84 -> -15274.38 | H74: ='Data Sheet'!G84 -> -15181.48 | I74: ='Data Sheet'!H84 -> -11572.49 | J74: ='Data Sheet'!I84 -> -25413.36 | ... L74: ='Data Sheet'!K84 -> -2156.43
B76: Net Cash Flow | C76: =_xlfn.IFERROR(C70+C72+C74,0) -> -244.75 | D76: =_xlfn.IFERROR(D70+D72+D74,0) -> 3253.94 | E76: =_xlfn.IFERROR(E70+E72+E74,0) -> -338.46 | F76: =_xlfn.IFERROR(F70+F72+F74,0) -> 4657.72 | G76: =_xlfn.IFERROR(G70+G72+G74,0) -> 2048.95 | H76: =_xlfn.IFERROR(H70+H72+H74,0) -> 396.72 | I76: =_xlfn.IFERROR(I70+I72+I74,0) -> 3156.45 | J76: =_xlfn.IFERROR(J70+J72+J74,0) -> -4968.19 | ... L76: =_xlfn.IFERROR(L70+L72+L74,0) -> 3204.24

Sheet Raw FS
B2: Particulars | C2: =_xlfn.IFERROR('Data Sheet 2'!C2,0) -> 42064 | D2: =_xlfn.IFERROR('Data Sheet 2'!D2,0) -> 42430 | E2: =_xlfn.IFERROR('Data Sheet 2'!E2,0) -> 42795 | F2: =_xlfn.IFERROR('Data Sheet 2'!F2,0) -> 43160 | G2: =_xlfn.IFERROR('Data Sheet 2'!G2,0) -> 43525 | H2: =_xlfn.IFERROR('Data Sheet 2'!H2,0) -> 43891 | I2: =_xlfn.IFERROR('Data Sheet 2'!I2,0) -> 44256 | J2: =_xlfn.IFERROR('Data Sheet 2'!J2,0) -> 44621 | ... N2: =_xlfn.IFERROR('Data Sheet 2'!N2,0) -> 46082
B4: =_xlfn.IFERROR('Data Sheet 2'!B3,0) -> Equity Capital | C4: =_xlfn.IFERROR('Data Sheet 2'!C3,0) -> 186 | D4: =_xlfn.IFERROR('Data Sheet 2'!D3,0) -> 186 | E4: =_xlfn.IFERROR('Data Sheet 2'!E3,0) -> 187 | F4: =_xlfn.IFERROR('Data Sheet 2'!F3,0) -> 280 | G4: =_xlfn.IFERROR('Data Sheet 2'!G3,0) -> 281 | H4: =_xlfn.IFERROR('Data Sheet 2'!H3,0) -> 281 | I4: =_xlfn.IFERROR('Data Sheet 2'!I3,0) -> 281 | ... N4: =_xlfn.IFERROR('Data Sheet 2'!N3,0) -> 275
B5: =_xlfn.IFERROR('Data Sheet 2'!B4,0) -> Reserves | C5: =_xlfn.IFERROR('Data Sheet 2'!C4,0) -> 40723 | D5: =_xlfn.IFERROR('Data Sheet 2'!D4,0) -> 43994 | E5: =_xlfn.IFERROR('Data Sheet 2'!E4,0) -> 50030 | F5: =_xlfn.IFERROR('Data Sheet 2'!F4,0) -> 54623 | G5: =_xlfn.IFERROR('Data Sheet 2'!G4,0) -> 62094 | H5: =_xlfn.IFERROR('Data Sheet 2'!H4,0) -> 66442 | I5: =_xlfn.IFERROR('Data Sheet 2'!I4,0) -> 75588 | ... N5: =_xlfn.IFERROR('Data Sheet 2'!N4,0) -> 109015
B6: =_xlfn.IFERROR('Data Sheet 2'!B5,0) -> Borrowings -
B7: =_xlfn.IFERROR('Data Sheet 2'!B6,0) -> Long term Borrowings | C7: =_xlfn.IFERROR('Data Sheet 2'!C6,0) -> 68469 | D7: =_xlfn.IFERROR('Data Sheet 2'!D6,0) -> 61224 | E7: =_xlfn.IFERROR('Data Sheet 2'!E6,0) -> 67341 | F7: =_xlfn.IFERROR('Data Sheet 2'!F6,0) -> 72915 | G7: =_xlfn.IFERROR('Data Sheet 2'!G6,0) -> 74121 | H7: =_xlfn.IFERROR('Data Sheet 2'!H6,0) -> 82331 | I7: =_xlfn.IFERROR('Data Sheet 2'!I6,0) -> 82120 | ... N7: =_xlfn.IFERROR('Data Sheet 2'!N6,0) -> 63739
B8: =_xlfn.IFERROR('Data Sheet 2'!B7,0) -> Short term Borrowings | C8: =_xlfn.IFERROR('Data Sheet 2'!C7,0) -> 16729 | D8: =_xlfn.IFERROR('Data Sheet 2'!D7,0) -> 14897 | E8: =_xlfn.IFERROR('Data Sheet 2'!E7,0) -> 16534 | F8: =_xlfn.IFERROR('Data Sheet 2'!F7,0) -> 19332 | G8: =_xlfn.IFERROR('Data Sheet 2'!G7,0) -> 29224 | H8: =_xlfn.IFERROR('Data Sheet 2'!H7,0) -> 35021 | I8: =_xlfn.IFERROR('Data Sheet 2'!I7,0) -> 27766 | ... N8: =_xlfn.IFERROR('Data Sheet 2'!N7,0) -> 34779
B9: =_xlfn.IFERROR('Data Sheet 2'!B8,0) -> Lease Liabilities | C9: =_xlfn.IFERROR('Data Sheet 2'!C8,0) -> 0 | D9: =_xlfn.IFERROR('Data Sheet 2'!D8,0) -> 0 | E9: =_xlfn.IFERROR('Data Sheet 2'!E8,0) -> 0 | F9: =_xlfn.IFERROR('Data Sheet 2'!F8,0) -> 0 | G9: =_xlfn.IFERROR('Data Sheet 2'!G8,0) -> 0 | H9: =_xlfn.IFERROR('Data Sheet 2'!H8,0) -> 2167 | I9: =_xlfn.IFERROR('Data Sheet 2'!I8,0) -> 2024 | ... N9: =_xlfn.IFERROR('Data Sheet 2'!N8,0) -> 3814
B10: =_xlfn.IFERROR('Data Sheet 2'!B9,0) -> Preference Capital | C10: =_xlfn.IFERROR('Data Sheet 2'!C9,0) -> 0 | D10: =_xlfn.IFERROR('Data Sheet 2'!D9,0) -> 1313 | E10: =_xlfn.IFERROR('Data Sheet 2'!E9,0) -> 1147 | F10: =_xlfn.IFERROR('Data Sheet 2'!F9,0) -> 905 | G10: =_xlfn.IFERROR('Data Sheet 2'!G9,0) -> 976 | H10: =_xlfn.IFERROR('Data Sheet 2'!H9,0) -> 1404 | I10: =_xlfn.IFERROR('Data Sheet 2'!I9,0) -> 1124 | ... N10: =_xlfn.IFERROR('Data Sheet 2'!N9,0) -> 0
B11: =_xlfn.IFERROR('Data Sheet 2'!B10,0) -> Other Borrowings | C11: =_xlfn.IFERROR('Data Sheet 2'!C10,0) -> 8431 | D11: =_xlfn.IFERROR('Data Sheet 2'!D10,0) -> 10702 | E11: =_xlfn.IFERROR('Data Sheet 2'!E10,0) -> 8932 | F11: =_xlfn.IFERROR('Data Sheet 2'!F10,0) -> 14372 | G11: =_xlfn.IFERROR('Data Sheet 2'!G10,0) -> 21234 | H11: =_xlfn.IFERROR('Data Sheet 2'!H10,0) -> 22251 | I11: =_xlfn.IFERROR('Data Sheet 2'!I10,0) -> 21596 | ... N11: =_xlfn.IFERROR('Data Sheet 2'!N10,0) -> 23166
B12: =_xlfn.IFERROR('Data Sheet 2'!B11,0) -> Other Liabilities -
B13: =_xlfn.IFERROR('Data Sheet 2'!B12,0) -> Non controlling int | C13: =_xlfn.IFERROR('Data Sheet 2'!C12,0) -> 4999 | D13: =_xlfn.IFERROR('Data Sheet 2'!D12,0) -> 2893 | E13: =_xlfn.IFERROR('Data Sheet 2'!E12,0) -> 3564 | F13: =_xlfn.IFERROR('Data Sheet 2'!F12,0) -> 5201 | G13: =_xlfn.IFERROR('Data Sheet 2'!G12,0) -> 6826 | H13: =_xlfn.IFERROR('Data Sheet 2'!H12,0) -> 9521 | I13: =_xlfn.IFERROR('Data Sheet 2'!I12,0) -> 12052 | ... N13: =_xlfn.IFERROR('Data Sheet 2'!N12,0) -> 19241
B14: =_xlfn.IFERROR('Data Sheet 2'!B13,0) -> Trade Payables | C14: =_xlfn.IFERROR('Data Sheet 2'!C13,0) -> 24650 | D14: =_xlfn.IFERROR('Data Sheet 2'!D13,0) -> 27004 | E14: =_xlfn.IFERROR('Data Sheet 2'!E13,0) -> 30295 | F14: =_xlfn.IFERROR('Data Sheet 2'!F13,0) -> 37797 | G14: =_xlfn.IFERROR('Data Sheet 2'!G13,0) -> 42995 | H14: =_xlfn.IFERROR('Data Sheet 2'!H13,0) -> 43644 | I14: =_xlfn.IFERROR('Data Sheet 2'!I13,0) -> 45745 | ... N14: =_xlfn.IFERROR('Data Sheet 2'!N13,0) -> 69456
B15: =_xlfn.IFERROR('Data Sheet 2'!B14,0) -> Advance from Customers | C15: =_xlfn.IFERROR('Data Sheet 2'!C14,0) -> 18502 | D15: =_xlfn.IFERROR('Data Sheet 2'!D14,0) -> 21376 | E15: =_xlfn.IFERROR('Data Sheet 2'!E14,0) -> 13956 | F15: =_xlfn.IFERROR('Data Sheet 2'!F14,0) -> 14860 | G15: =_xlfn.IFERROR('Data Sheet 2'!G14,0) -> 17271 | H15: =_xlfn.IFERROR('Data Sheet 2'!H14,0) -> 16353 | I15: =_xlfn.IFERROR('Data Sheet 2'!I14,0) -> 15876 | ... N15: =_xlfn.IFERROR('Data Sheet 2'!N14,0) -> 39586
B16: =_xlfn.IFERROR('Data Sheet 2'!B15,0) -> Other liability items | C16: =_xlfn.IFERROR('Data Sheet 2'!C15,0) -> 10816 | D16: =_xlfn.IFERROR('Data Sheet 2'!D15,0) -> 10500 | E16: =_xlfn.IFERROR('Data Sheet 2'!E15,0) -> 19585 | F16: =_xlfn.IFERROR('Data Sheet 2'!F15,0) -> 22954 | G16: =_xlfn.IFERROR('Data Sheet 2'!G15,0) -> 23014 | H16: =_xlfn.IFERROR('Data Sheet 2'!H15,0) -> 27272 | I16: =_xlfn.IFERROR('Data Sheet 2'!I15,0) -> 25924 | ... N16: =_xlfn.IFERROR('Data Sheet 2'!N15,0) -> 89312
B17: =_xlfn.IFERROR('Data Sheet 2'!B16,0) -> Total Liabilities | C17: =SUM(C4:C16) -> 193505 | D17: =SUM(D4:D16) -> 194089 | E17: =SUM(E4:E16) -> 211571 | F17: =SUM(F4:F16) -> 243239 | G17: =SUM(G4:G16) -> 278036 | H17: =SUM(H4:H16) -> 306687 | I17: =SUM(I4:I16) -> 310096 | J17: =SUM(J4:J16) -> 319028 | ... N17: =SUM(N4:N16) -> 452383
B19: =_xlfn.IFERROR('Data Sheet 2'!B17,0) -> Fixed Assets -
B20: =_xlfn.IFERROR('Data Sheet 2'!B18,0) -> Land | C20: =_xlfn.IFERROR('Data Sheet 2'!C18,0) -> 1822 | D20: =_xlfn.IFERROR('Data Sheet 2'!D18,0) -> 1071 | E20: =_xlfn.IFERROR('Data Sheet 2'!E18,0) -> 1038 | F20: =_xlfn.IFERROR('Data Sheet 2'!F18,0) -> 1025 | G20: =_xlfn.IFERROR('Data Sheet 2'!G18,0) -> 1362 | H20: =_xlfn.IFERROR('Data Sheet 2'!H18,0) -> 1571 | I20: =_xlfn.IFERROR('Data Sheet 2'!I18,0) -> 1548 | ... N20: =_xlfn.IFERROR('Data Sheet 2'!N18,0) -> 1803
B21: =_xlfn.IFERROR('Data Sheet 2'!B19,0) -> Building | C21: =_xlfn.IFERROR('Data Sheet 2'!C19,0) -> 5942 | D21: =_xlfn.IFERROR('Data Sheet 2'!D19,0) -> 3705 | E21: =_xlfn.IFERROR('Data Sheet 2'!E19,0) -> 3832 | F21: =_xlfn.IFERROR('Data Sheet 2'!F19,0) -> 11166 | G21: =_xlfn.IFERROR('Data Sheet 2'!G19,0) -> 12014 | H21: =_xlfn.IFERROR('Data Sheet 2'!H19,0) -> 6261 | I21: =_xlfn.IFERROR('Data Sheet 2'!I19,0) -> 6678 | ... N21: =_xlfn.IFERROR('Data Sheet 2'!N19,0) -> 11326
B22: =_xlfn.IFERROR('Data Sheet 2'!B20,0) -> Plant Machinery | C22: =_xlfn.IFERROR('Data Sheet 2'!C20,0) -> 15771 | D22: =_xlfn.IFERROR('Data Sheet 2'!D20,0) -> 6376 | E22: =_xlfn.IFERROR('Data Sheet 2'!E20,0) -> 6796 | F22: =_xlfn.IFERROR('Data Sheet 2'!F20,0) -> 637 | G22: =_xlfn.IFERROR('Data Sheet 2'!G20,0) -> 0 | H22: =_xlfn.IFERROR('Data Sheet 2'!H20,0) -> 7899 | I22: =_xlfn.IFERROR('Data Sheet 2'!I20,0) -> 10077 | ... N22: =_xlfn.IFERROR('Data Sheet 2'!N20,0) -> 15800
B23: =_xlfn.IFERROR('Data Sheet 2'!B21,0) -> Ships Vessels | C23: =_xlfn.IFERROR('Data Sheet 2'!C21,0) -> 787 | D23: =_xlfn.IFERROR('Data Sheet 2'!D21,0) -> 38 | E23: =_xlfn.IFERROR('Data Sheet 2'!E21,0) -> 37 | F23: =_xlfn.IFERROR('Data Sheet 2'!F21,0) -> 37 | G23: =_xlfn.IFERROR('Data Sheet 2'!G21,0) -> 130 | H23: =_xlfn.IFERROR('Data Sheet 2'!H21,0) -> 882 | I23: =_xlfn.IFERROR('Data Sheet 2'!I21,0) -> 947 | ... N23: =_xlfn.IFERROR('Data Sheet 2'!N21,0) -> 1696
B24: =_xlfn.IFERROR('Data Sheet 2'!B22,0) -> Equipments | C24: =_xlfn.IFERROR('Data Sheet 2'!C22,0) -> 512 | D24: =_xlfn.IFERROR('Data Sheet 2'!D22,0) -> 222 | E24: =_xlfn.IFERROR('Data Sheet 2'!E22,0) -> 264 | F24: =_xlfn.IFERROR('Data Sheet 2'!F22,0) -> 321 | G24: =_xlfn.IFERROR('Data Sheet 2'!G22,0) -> 376 | H24: =_xlfn.IFERROR('Data Sheet 2'!H22,0) -> 543 | I24: =_xlfn.IFERROR('Data Sheet 2'!I22,0) -> 590 | ... N24: =_xlfn.IFERROR('Data Sheet 2'!N22,0) -> 1060
B25: =_xlfn.IFERROR('Data Sheet 2'!B23,0) -> Computers | C25: =_xlfn.IFERROR('Data Sheet 2'!C23,0) -> 1111 | D25: =_xlfn.IFERROR('Data Sheet 2'!D23,0) -> 457 | E25: =_xlfn.IFERROR('Data Sheet 2'!E23,0) -> 540 | F25: =_xlfn.IFERROR('Data Sheet 2'!F23,0) -> 0 | G25: =_xlfn.IFERROR('Data Sheet 2'!G23,0) -> 849 | H25: =_xlfn.IFERROR('Data Sheet 2'!H23,0) -> 1425 | I25: =_xlfn.IFERROR('Data Sheet 2'!I23,0) -> 1615 | ... N25: =_xlfn.IFERROR('Data Sheet 2'!N23,0) -> 3152
B26: =_xlfn.IFERROR('Data Sheet 2'!B24,0) -> Furniture n fittings | C26: =_xlfn.IFERROR('Data Sheet 2'!C24,0) -> 650 | D26: =_xlfn.IFERROR('Data Sheet 2'!D24,0) -> 293 | E26: =_xlfn.IFERROR('Data Sheet 2'!E24,0) -> 317 | F26: =_xlfn.IFERROR('Data Sheet 2'!F24,0) -> 393 | G26: =_xlfn.IFERROR('Data Sheet 2'!G24,0) -> 413 | H26: =_xlfn.IFERROR('Data Sheet 2'!H24,0) -> 475 | I26: =_xlfn.IFERROR('Data Sheet 2'!I24,0) -> 485 | ... N26: =_xlfn.IFERROR('Data Sheet 2'!N24,0) -> 754
B27: =_xlfn.IFERROR('Data Sheet 2'!B25,0) -> Railway sidings | C27: =_xlfn.IFERROR('Data Sheet 2'!C25,0) -> 0 | D27: =_xlfn.IFERROR('Data Sheet 2'!D25,0) -> 0 | E27: =_xlfn.IFERROR('Data Sheet 2'!E25,0) -> 0 | F27: =_xlfn.IFERROR('Data Sheet 2'!F25,0) -> 0 | G27: =_xlfn.IFERROR('Data Sheet 2'!G25,0) -> 0 | H27: =_xlfn.IFERROR('Data Sheet 2'!H25,0) -> 0 | I27: =_xlfn.IFERROR('Data Sheet 2'!I25,0) -> 0 | ... N27: =_xlfn.IFERROR('Data Sheet 2'!N25,0) -> 0
B28: =_xlfn.IFERROR('Data Sheet 2'!B26,0) -> Vehicles | C28: =_xlfn.IFERROR('Data Sheet 2'!C26,0) -> 851 | D28: =_xlfn.IFERROR('Data Sheet 2'!D26,0) -> 487 | E28: =_xlfn.IFERROR('Data Sheet 2'!E26,0) -> 450 | F28: =_xlfn.IFERROR('Data Sheet 2'!F26,0) -> 658 | G28: =_xlfn.IFERROR('Data Sheet 2'!G26,0) -> 682 | H28: =_xlfn.IFERROR('Data Sheet 2'!H26,0) -> 681 | I28: =_xlfn.IFERROR('Data Sheet 2'!I26,0) -> 658 | ... N28: =_xlfn.IFERROR('Data Sheet 2'!N26,0) -> 1380
B29: =_xlfn.IFERROR('Data Sheet 2'!B27,0) -> Intangible Assets | C29: =_xlfn.IFERROR('Data Sheet 2'!C27,0) -> 2478 | D29: =_xlfn.IFERROR('Data Sheet 2'!D27,0) -> 1658 | E29: =_xlfn.IFERROR('Data Sheet 2'!E27,0) -> 1512 | F29: =_xlfn.IFERROR('Data Sheet 2'!F27,0) -> 1736 | G29: =_xlfn.IFERROR('Data Sheet 2'!G27,0) -> 5729 | H29: =_xlfn.IFERROR('Data Sheet 2'!H27,0) -> 24817 | I29: =_xlfn.IFERROR('Data Sheet 2'!I27,0) -> 25195 | ... N29: =_xlfn.IFERROR('Data Sheet 2'!N27,0) -> 9432
B30: =_xlfn.IFERROR('Data Sheet 2'!B28,0) -> Other fixed assets | C30: =_xlfn.IFERROR('Data Sheet 2'!C28,0) -> 15861 | D30: =_xlfn.IFERROR('Data Sheet 2'!D28,0) -> 2216 | E30: =_xlfn.IFERROR('Data Sheet 2'!E28,0) -> 5921 | F30: =_xlfn.IFERROR('Data Sheet 2'!F28,0) -> 8448 | G30: =_xlfn.IFERROR('Data Sheet 2'!G28,0) -> 7091 | H30: =_xlfn.IFERROR('Data Sheet 2'!H28,0) -> 8568 | I30: =_xlfn.IFERROR('Data Sheet 2'!I28,0) -> 8784 | ... N30: =_xlfn.IFERROR('Data Sheet 2'!N28,0) -> 7487
B31: =_xlfn.IFERROR('Data Sheet 2'!B29,0) -> Gross Block | C31: =_xlfn.IFERROR('Data Sheet 2'!C29,0) -> 45783 | D31: =_xlfn.IFERROR('Data Sheet 2'!D29,0) -> 16522 | E31: =_xlfn.IFERROR('Data Sheet 2'!E29,0) -> 20706 | F31: =_xlfn.IFERROR('Data Sheet 2'!F29,0) -> 24422 | G31: =_xlfn.IFERROR('Data Sheet 2'!G29,0) -> 28644 | H31: =_xlfn.IFERROR('Data Sheet 2'!H29,0) -> 53121 | I31: =_xlfn.IFERROR('Data Sheet 2'!I29,0) -> 56577 | ... N31: =_xlfn.IFERROR('Data Sheet 2'!N29,0) -> 53890
B32: =_xlfn.IFERROR('Data Sheet 2'!B30,0) -> Accumulated Depreciation | C32: =_xlfn.IFERROR('Data Sheet 2'!C30,0) -> 10806 | D32: =_xlfn.IFERROR('Data Sheet 2'!D30,0) -> 2347 | E32: =_xlfn.IFERROR('Data Sheet 2'!E30,0) -> 4029 | F32: =_xlfn.IFERROR('Data Sheet 2'!F30,0) -> 5842 | G32: =_xlfn.IFERROR('Data Sheet 2'!G30,0) -> 7450 | H32: =_xlfn.IFERROR('Data Sheet 2'!H30,0) -> 9468 | I32: =_xlfn.IFERROR('Data Sheet 2'!I30,0) -> 12258 | ... N32: =_xlfn.IFERROR('Data Sheet 2'!N30,0) -> 23023
B33: Net Block | C33: =C31-C32 -> 34977 | D33: =D31-D32 -> 14175 | E33: =E31-E32 -> 16677 | F33: =F31-F32 -> 18580 | G33: =G31-G32 -> 21194 | H33: =H31-H32 -> 43653 | I33: =I31-I32 -> 44319 | J33: =J31-J32 -> 42945 | ... N33: =N31-N32 -> 30867
B35: =_xlfn.IFERROR('Data Sheet 2'!B31,0) -> CWIP | C35: =_xlfn.IFERROR('Data Sheet 2'!C31,0) -> 14993 | D35: =_xlfn.IFERROR('Data Sheet 2'!D31,0) -> 10974 | E35: =_xlfn.IFERROR('Data Sheet 2'!E31,0) -> 13298 | F35: =_xlfn.IFERROR('Data Sheet 2'!F31,0) -> 13443 | G35: =_xlfn.IFERROR('Data Sheet 2'!G31,0) -> 13919 | H35: =_xlfn.IFERROR('Data Sheet 2'!H31,0) -> 3311 | I35: =_xlfn.IFERROR('Data Sheet 2'!I31,0) -> 500 | ... N35: =_xlfn.IFERROR('Data Sheet 2'!N31,0) -> 3311
B36: =_xlfn.IFERROR('Data Sheet 2'!B32,0) -> Investments | C36: =_xlfn.IFERROR('Data Sheet 2'!C32,0) -> 9612 | D36: =_xlfn.IFERROR('Data Sheet 2'!D32,0) -> 15465 | E36: =_xlfn.IFERROR('Data Sheet 2'!E32,0) -> 19753 | F36: =_xlfn.IFERROR('Data Sheet 2'!F32,0) -> 15311 | G36: =_xlfn.IFERROR('Data Sheet 2'!G32,0) -> 20907 | H36: =_xlfn.IFERROR('Data Sheet 2'!H32,0) -> 20047 | I36: =_xlfn.IFERROR('Data Sheet 2'!I32,0) -> 39627 | ... N36: =_xlfn.IFERROR('Data Sheet 2'!N32,0) -> 68377
B38: =_xlfn.IFERROR('Data Sheet 2'!B33,0) -> Other Assets -
B39: =_xlfn.IFERROR('Data Sheet 2'!B34,0) -> Inventories | C39: =_xlfn.IFERROR('Data Sheet 2'!C34,0) -> 6508 | D39: =_xlfn.IFERROR('Data Sheet 2'!D34,0) -> 4854 | E39: =_xlfn.IFERROR('Data Sheet 2'!E34,0) -> 4140 | F39: =_xlfn.IFERROR('Data Sheet 2'!F34,0) -> 4848 | G39: =_xlfn.IFERROR('Data Sheet 2'!G34,0) -> 6414 | H39: =_xlfn.IFERROR('Data Sheet 2'!H34,0) -> 5747 | I39: =_xlfn.IFERROR('Data Sheet 2'!I34,0) -> 5821 | ... N39: =_xlfn.IFERROR('Data Sheet 2'!N34,0) -> 9531
B40: =_xlfn.IFERROR('Data Sheet 2'!B35,0) -> Trade receivables + | C40: =_xlfn.IFERROR('Data Sheet 2'!C35,0) -> 30089 | D40: =_xlfn.IFERROR('Data Sheet 2'!D35,0) -> 26025 | E40: =_xlfn.IFERROR('Data Sheet 2'!E35,0) -> 28689 | F40: =_xlfn.IFERROR('Data Sheet 2'!F35,0) -> 33117 | G40: =_xlfn.IFERROR('Data Sheet 2'!G35,0) -> 36846 | H40: =_xlfn.IFERROR('Data Sheet 2'!H35,0) -> 40732 | I40: =_xlfn.IFERROR('Data Sheet 2'!I35,0) -> 42230 | ... N40: =_xlfn.IFERROR('Data Sheet 2'!N35,0) -> 60461
B41: =_xlfn.IFERROR('Data Sheet 2'!B36,0) -> Cash Equivalents | C41: =_xlfn.IFERROR('Data Sheet 2'!C36,0) -> 5756 | D41: =_xlfn.IFERROR('Data Sheet 2'!D36,0) -> 5390 | E41: =_xlfn.IFERROR('Data Sheet 2'!E36,0) -> 5306 | F41: =_xlfn.IFERROR('Data Sheet 2'!F36,0) -> 8033 | G41: =_xlfn.IFERROR('Data Sheet 2'!G36,0) -> 11726 | H41: =_xlfn.IFERROR('Data Sheet 2'!H36,0) -> 15118 | I41: =_xlfn.IFERROR('Data Sheet 2'!I36,0) -> 16242 | ... N41: =_xlfn.IFERROR('Data Sheet 2'!N36,0) -> 20848
B42: =_xlfn.IFERROR('Data Sheet 2'!B37,0) -> Loans n Advances | C42: =_xlfn.IFERROR('Data Sheet 2'!C37,0) -> 11219 | D42: =_xlfn.IFERROR('Data Sheet 2'!D37,0) -> 18526 | E42: =_xlfn.IFERROR('Data Sheet 2'!E37,0) -> 24733 | F42: =_xlfn.IFERROR('Data Sheet 2'!F37,0) -> 31865 | G42: =_xlfn.IFERROR('Data Sheet 2'!G37,0) -> 41938 | H42: =_xlfn.IFERROR('Data Sheet 2'!H37,0) -> 40958 | I42: =_xlfn.IFERROR('Data Sheet 2'!I37,0) -> 40786 | ... N42: =_xlfn.IFERROR('Data Sheet 2'!N37,0) -> 40747
B43: =_xlfn.IFERROR('Data Sheet 2'!B38,0) -> Other asset items | C43: =_xlfn.IFERROR('Data Sheet 2'!C38,0) -> 80351 | D43: =_xlfn.IFERROR('Data Sheet 2'!D38,0) -> 98680 | E43: =_xlfn.IFERROR('Data Sheet 2'!E38,0) -> 98975 | F43: =_xlfn.IFERROR('Data Sheet 2'!F38,0) -> 118042 | G43: =_xlfn.IFERROR('Data Sheet 2'!G38,0) -> 125092 | H43: =_xlfn.IFERROR('Data Sheet 2'!H38,0) -> 137121 | I43: =_xlfn.IFERROR('Data Sheet 2'!I38,0) -> 120571 | ... N43: =_xlfn.IFERROR('Data Sheet 2'!N38,0) -> 218241
B44: =_xlfn.IFERROR('Data Sheet 2'!B39,0) -> Total Assets | C44: =SUM(C33:C43) -> 193505 | D44: =SUM(D33:D43) -> 194089 | E44: =SUM(E33:E43) -> 211571 | F44: =SUM(F33:F43) -> 243239 | G44: =SUM(G33:G43) -> 278036 | H44: =SUM(H33:H43) -> 306687 | I44: =SUM(I33:I43) -> 310096 | J44: =SUM(J33:J43) -> 319028 | ... N44: =SUM(N33:N43) -> 452383
B46: Check | C46: =C44=C17 -> TRUE | D46: =D44=D17 -> TRUE | E46: =E44=E17 -> TRUE | F46: =F44=F17 -> TRUE | G46: =G44=G17 -> TRUE | H46: =H44=H17 -> TRUE | I46: =I44=I17 -> TRUE | J46: =J44=J17 -> TRUE | ... N46: =N44=N17 -> TRUE

Sheet Data Sheet
A1: COMPANY NAME | B1: LARSEN & TOUBRO LTD | E1: =IF(B2<>B3,"A NEW VERSION OF THE WORKSHEET IS AVAILABLE","")
A2: LATEST VERSION | B2: 2.1 | E2: PLEASE DO NOT MAKE ANY CHANGES TO THIS SHEET
A3: CURRENT VERSION | B3: 2.1
A5: META
A6: Number of shares | B6: =IF(B9>0,B9/B8,0) -> 137.5294
A7: Face Value | B7: 2
A8: Current Price | B8: 3785.6
A9: Market Capitalization | B9: 520631.29
A15: PROFIT & LOSS | B15: =B26+B34 -> 19616.34 | K15: =K17-K18-K20-K21-K22-K23-K19 -> 38354.9
A16: Report Date | B16: 42825 | C16: 43190 | D16: 43555 | E16: 43921 | F16: 44286 | G16: 44651 | H16: 45016 | I16: 45382 | J16: 45747 | K16: 46112
A17: Sales | B17: 109311.81 | C17: 119683.16 | D17: 135220.29 | E17: 145452.36 | F17: 135979.03 | G17: 156521.23 | H17: 183340.7 | I17: 221112.91 | J17: 255734.45 | K17: 285874.36
A18: Raw Material Cost | B18: 36648.54 | C18: 40876.24 | D18: 46889.87 | E18: 46705.87 | F18: 41333.86 | G18: 51676.55 | H18: 63285.32 | I18: 75319.99 | J18: 92583.6 | K18: 97682.71
A19: Change in Inventory | B19: -84 | C19: 1315.23 | D19: 731.11 | E19: -647.7 | F19: -343.37 | G19: 2076.6 | H19: 3156.64 | I19: -1021.07 | J19: 410.79 | K19: 1963.12
A20: Power and Fuel | B20: 1423.19 | C20: 1399.62 | D20: 2205.6 | E20: 2079.84 | F20: 1581.33 | G20: 2267.26 | H20: 2655.76 | I20: 2745.19 | J20: 2299.81 | K20: 2276.53
A21: Other Mfr. Exp | B21: 32976.99 | C21: 35464.04 | D21: 38772.73 | E21: 38942.54 | F21: 35725.84 | G21: 41993.25 | H21: 47648.63 | I21: 61400.51 | J21: 70064.42 | K21: 87563.9
A22: Employee Cost | B22: 13857.57 | C22: 15277.07 | D22: 17475.35 | E22: 23125.64 | F22: 24758.51 | G22: 29701.71 | H22: 37222.87 | I22: 41178.2 | J22: 46774.52 | K22: 52191.85
A23: Selling and admin | B23: 4273.19 | C23: 4576.99 | D23: 5074.72 | E23: 5255.1 | F23: 3039.18 | G23: 3575.28 | H23: 4650.22 | I23: 4908.12 | J23: 5598.1 | K23: 5841.35
A24: Other Expenses | B24: 3427.92 | C24: 3293.09 | D24: 2667.31 | E24: 4142.57 | F24: 5736.7 | G24: 5069.89 | H24: 3868.52 | I24: 5781.71 | J24: 4397.89 | K24: 6870.44
A25: Other Income | B25: 1465.54 | C25: 1464.93 | D25: 2700.61 | E25: 3015.47 | F25: 8111.25 | G25: 2364.01 | H25: 2890.7 | I25: 4953.49 | J25: 3197.85 | K25: 4985.8
A26: Depreciation | B26: 2369.93 | C26: 2223.48 | D26: 1923.03 | E26: 2462.27 | F26: 2904.21 | G26: 2947.95 | H26: 3502.25 | I26: 3682.33 | J26: 4121.18 | K26: 4364.75
A27: Interest | B27: 6828.66 | C27: 7713.63 | D27: 9338.73 | E27: 11020.78 | F27: 11749.58 | G27: 9234.98 | H27: 9445.44 | I27: 9512.17 | J27: 9924.78 | K27: 10055.94
... A31: Dividend Amount | B31: 1306.13 | C31: 2242.16 | D31: 2524.95 | E31: 2527.02 | F31: 5056.38 | G31: 3091.11 | H31: 3373.2 | I31: 4673.81 | J31: 4675.68 | K31: 5227.47
A32: Effective Tax Rate | B32: =B29/B28 -> 0.22578021 | C32: =C29/C28 -> 0.27483684 | D32: =D29/D28 -> 0.28431904 | E32: =E29/E28 -> 0.23167054 | F32: =F29/F28 -> 0.23707833 | G32: =G29/G28 -> 0.29002613 | H32: =H29/H28 -> 0.26209318 | I32: =I29/I28 -> 0.24113484 | ... K32: =K29/K28 -> 0.26241376
A34: EBITDA | B34: =+B30+B29+B27+B26 -> 17246.41 | C34: =+C30+C29+C27+C26 -> 20505.84 | D34: =+D30+D29+D27+D26 -> 24233.98 | E34: =+E30+E29+E27+E26 -> 26295.28 | F34: =+F30+F29+F27+F26 -> 30247.54 | G34: =+G30+G29+G27+G26 -> 25056.18 | H34: =+H30+H29+H27+H26 -> 27902.57 | I34: =+I30+I29+I27+I26 -> 31201 | ... K34: =+K30+K29+K27+K26 -> 37321.09
A40: Quarters
A41: Report Date | B41: 45291 | C41: 45382 | D41: 45473 | E41: 45565 | F41: 45657 | G41: 45747 | H41: 45838 | I41: 45930 | J41: 46022 | K41: 46112
A42: Sales | B42: 55127.82 | C42: 67078.68 | D42: 55119.82 | E42: 61554.58 | F42: 64667.78 | G42: 74392.28 | H42: 63678.92 | I42: 67983.53 | J42: 71449.7 | K42: 82762.16
A43: Expenses | B43: 47929.17 | C43: 58425.64 | D43: 48074 | E43: 53637.53 | F43: 56769.62 | G43: 64516.34 | H43: 55654.91 | I43: 59470.29 | J43: 62259.49 | K43: 72343.14
A44: Other Income | B44: 837.75 | C44: 1135.35 | D44: 920.64 | E44: 1101.27 | F44: 967.87 | G44: 1609.83 | H44: 1356.78 | I44: 1384.28 | J44: -350.05 | K44: 1647.24
A45: Depreciation | B45: 920.75 | C45: 1021.2 | D45: 997.92 | E45: 1023.84 | F45: 1047 | G45: 1052.42 | H45: 1033.3 | I45: 1091.77 | J45: 1071.74 | K45: 1167.95
A46: Interest | B46: 2343.82 | C46: 2345.35 | D46: 2291.89 | E46: 2439.39 | F46: 2486 | G46: 2419.33 | H46: 2487.96 | I46: 2469.64 | J46: 2398.53 | K46: 2488.03
A47: Profit before tax | B47: 4771.83 | C47: 6421.84 | D47: 4676.65 | E47: 5555.09 | F47: 5333.03 | G47: 8014.02 | H47: 5859.53 | I47: 6336.11 | J47: 5369.89 | K47: 8410.28
A48: Tax | B48: 1177.32 | C48: 1418.3 | D48: 1236.54 | E48: 1442.28 | F48: 1332 | G48: 1880.58 | H48: 1533.96 | I48: 1649.02 | J48: 1540.66 | K48: 2092.75
A49: Net profit | B49: 2947.36 | C49: 4396.12 | D49: 2785.72 | E49: 3395.29 | F49: 3358.84 | G49: 5497.26 | H49: 3617.19 | I49: 3926.09 | J49: 3215.11 | K49: 5325.6
A50: Operating Profit | B50: 7198.65 | C50: 8653.04 | D50: 7045.82 | E50: 7917.05 | F50: 7898.16 | G50: 9875.94 | H50: 8024.01 | I50: 8513.24 | J50: 9190.21 | K50: 10419.02
A51: EBITDA | B51: =B49+B48+B46+B45 -> 7389.25 | C51: =C49+C48+C46+C45 -> 9180.97 | D51: =D49+D48+D46+D45 -> 7312.07 | E51: =E49+E48+E46+E45 -> 8300.8 | F51: =F49+F48+F46+F45 -> 8223.84 | G51: =G49+G48+G46+G45 -> 10849.59 | H51: =H49+H48+H46+H45 -> 8672.41 | I51: =I49+I48+I46+I45 -> 9136.52 | ... K51: =K49+K48+K46+K45 -> 11074.33
A55: BALANCE SHEET
A56: Report Date | B56: 42825 | C56: 43190 | D56: 43555 | E56: 43921 | F56: 44286 | G56: 44651 | H56: 45016 | I56: 45382 | J56: 45747 | K56: 46112
A57: Equity Share Capital | B57: 186.59 | C57: 280.27 | D57: 280.55 | E57: 280.78 | F57: 280.91 | G57: 281.01 | H57: 281.1 | I57: 274.93 | J57: 275.04 | K57: 275.13
A58: Reserves | B58: 50029.93 | C58: 54623.23 | D58: 62094.25 | E58: 66442.44 | F58: 75587.62 | G58: 82126.65 | H58: 89044.85 | I58: 86084.31 | J58: 97380.56 | K58: 109014.67
A59: Borrowings | B59: 93953.95 | C59: 107524.08 | D59: 125555.17 | E59: 143173.67 | F59: 134629.08 | G59: 125508.08 | H59: 120650.44 | I59: 116322.22 | J59: 132408.92 | K59: 125496.59
A60: Other Liabilities | B60: 67400.18 | C60: 80811.95 | D60: 90106.26 | E60: 96790.2 | F60: 99597.44 | G60: 111112.17 | H60: 119745.49 | I60: 136920.88 | J60: 149049.57 | K60: 217596.38
A61: Total | B61: 211570.65 | C61: 243239.53 | D61: 278036.23 | E61: 306687.09 | F61: 310095.05 | G61: 319027.91 | H61: 329721.88 | I61: 339602.34 | J61: 379114.09 | K61: 452382.77
A62: Net Block | B62: 16677.11 | C62: 18580.19 | D62: 21193.94 | E62: 43653.38 | F62: 44319.32 | G62: 42945.01 | H62: 42641 | I62: 42963.82 | J62: 44055.45 | K62: 30866.91
A63: Capital Work in Progress | B63: 13297.94 | C63: 13443.43 | D63: 13919.49 | E63: 3311.09 | F63: 500.39 | G63: 1249.55 | H63: 3065.57 | I63: 3045.01 | J63: 2588.68 | K63: 3310.95
A64: Investments | B64: 19753.02 | C64: 15311.31 | D64: 20907.1 | E64: 20047.48 | F64: 39626.63 | G64: 39395.18 | H64: 44798.31 | I64: 45647.82 | J64: 54805.27 | K64: 68376.79
A65: Other Assets | B65: 161842.58 | C65: 195904.6 | D65: 222015.7 | E65: 239675.14 | F65: 225648.71 | G65: 235438.17 | H65: 239217 | I65: 247945.69 | J65: 277664.69 | K65: 349828.12
A66: Total | B66: 211570.65 | C66: 243239.53 | D66: 278036.23 | E66: 306687.09 | F66: 310095.05 | G66: 319027.91 | H66: 329721.88 | I66: 339602.34 | J66: 379114.09 | K66: 452382.77
A67: Receivables | B67: 28688.97 | C67: 33116.98 | D67: 36845.87 | E67: 40731.52 | F67: 42229.78 | G67: 46139.32 | H67: 44731.53 | I67: 48770.95 | J67: 53713.68 | K67: 60461.26
... A70: No. of Equity Shares | B70: 932965803 | C70: 1401369456 | D70: 1402729385 | E70: 1403892022 | F70: 1404555297 | G70: 1405029123 | H70: 1405482190 | I70: 1374668619 | J70: 1375192165 | K70: 1375632190
A71: New Bonus Shares | C71: 466764755
A72: Face value | B72: 2 | C72: 2 | D72: 2 | E72: 2 | F72: 2 | G72: 2 | H72: 2 | I72: 2 | J72: 2 | K72: 2
H73: =H62-G62+H45 -> 729.29 | I73: =I62-H62+I45 -> 1414.59 | J73: =J62-I62+J45 -> 2163.37 | K73: =K62-J62+K45 -> -12020.59
A80: CASH FLOW:
A81: Report Date | B81: 42825 | C81: 43190 | D81: 43555 | E81: 43921 | F81: 44286 | G81: 44651 | H81: 45016 | I81: 45382 | J81: 45747 | K81: 46112
A82: Cash from Operating Activity | B82: 6655.26 | C82: -10031.02 | D82: -4755.83 | E82: 6693.88 | F82: 23073.82 | G82: 19163.58 | H82: 22776.96 | I82: 18266.28 | J82: 9151.35 | K82: 16740.97
A83: Cash from Investing Activity | B83: -9795.94 | C83: 3914.5 | D83: -11022.8 | E83: -8407.71 | F83: -5750.49 | G83: -3585.38 | H83: -8048.02 | I83: 2178.89 | J83: -15479.47 | K83: -11380.3
A84: Cash from Financing Activity | B84: 2895.93 | C84: 9370.46 | D84: 15440.17 | E84: 6371.55 | F84: -15274.38 | G84: -15181.48 | H84: -11572.49 | I84: -25413.36 | J84: 6556.62 | K84: -2156.43
A85: Net Cash Flow | B85: -244.75 | C85: 3253.94 | D85: -338.46 | E85: 4657.72 | F85: 2048.95 | G85: 396.72 | H85: 3156.45 | I85: -4968.19 | J85: 228.5 | K85: 3204.24
A90: PRICE: | B90: 1049.93 | C90: 1310.9 | D90: 1385.3 | E90: 808.5 | F90: 1418.9 | G90: 1767.65 | H90: 2164.2 | I90: 3763.9 | J90: 3492.3 | K90: 3504.1
A92: DERIVED:
A93: Adjusted Equity Shares in Cr | B93: 139.94 | C93: 140.14 | D93: 140.27 | E93: 140.39 | F93: 140.46 | G93: 140.5 | H93: 140.55 | I93: 137.47 | J93: 137.52 | K93: 137.56

Sheet CFS
B2: 42064 | C2: 42430 | D2: 42795 | E2: 43160 | F2: 43525 | G2: 43891 | H2: 44256 | I2: 44621 | J2: 44986 | K2: 45352 | L2: 45717 | M2: 46082
A3: Cash from Operating Activity - | B3: -1365 | C3: -3240 | D3: 6655 | E3: -10031 | F3: -4756 | G3: 6694 | H3: 23074 | I3: 19164 | J3: 22777 | K3: 18266 | L3: 9151 | M3: 16741
A4: Profit from operations | B4: 10198 | C4: 10485 | D4: 11255 | E4: 13248 | F4: 16073 | G4: 18524 | H4: 16347 | I4: 18946 | J4: 22525 | K4: 24931 | L4: 29981 | M4: 33230
A5: Receivables | B5: -9737 | C5: -9450 | D5: -2471 | E5: -14501 | F5: -9241 | G5: -11278 | H5: 3012 | I5: -9852 | J5: -4495 | K5: -10643 | L5: -10316 | M5: -28151
A6: Inventory | B6: -983 | C6: 217 | D6: 1510 | E6: -642 | F6: 331 | G6: 353 | H6: 349 | I6: -74 | J6: -476 | K6: 245 | L6: -540 | M6: -2201
A7: Payables | B7: 9120 | C7: 9308 | D7: 5307 | E7: 11727 | F7: 6819 | G7: 3134 | H7: 2220 | I7: 9678 | J7: 5413 | K7: 14601 | L7: 9835 | M7: 45128
A8: Loans Advances | B8: -6984 | C8: -10585 | D8: -5744 | E8: -16459 | F8: -13855 | G8: 7 | H8: 4618 | I8: 5005 | J8: 4937 | K8: -5588 | L8: -14208 | M8: -25233
A9: Working capital changes | B9: -8584 | C9: -10510 | D9: -1398 | E9: -19876 | F9: -15946 | G9: -7784 | H9: 10198 | I9: 4757 | J9: 5379 | K9: -1385 | L9: -15229 | M9: -10458
A10: Direct taxes | B10: -2979 | C10: -3215 | D10: -3202 | E10: -3403 | F10: -4883 | G10: -4046 | H10: -3471 | I10: -4539 | J10: -5127 | K10: -5280 | L10: -5601 | M10: -6031
A11: Cash from Investing Activity - | B11: -4778 | C11: -4627 | D11: -9796 | E11: 3914 | F11: -11023 | G11: -8408 | H11: -5750 | I11: -3585 | J11: -8048 | K11: 2179 | L11: -15479 | M11: -11380
A12: Fixed assets purchased | B12: -6252 | C12: -4322 | D12: -2977 | E12: -2877 | F12: -4307 | G12: -3437 | H12: -1808 | I12: -3111 | J12: -4144 | K12: -4517 | L12: -4419 | M12: -4809
A13: Fixed assets sold | B13: 158 | C13: 198 | D13: 156 | E13: 862 | F13: 808 | G13: 137 | H13: 885 | I13: 71 | J13: 350 | K13: 306 | L13: 878 | M13: 341
A14: Investments purchased | B14: -830 | C14: -746 | D14: -7882 | E14: -1291 | F14: -4917 | G14: -1857 | H14: -18715 | I14: -2156 | J14: -9120 | K14: -4889 | L14: -8235 | M14: -12946
... A32: CFO/OP | B32: 0.1 | C32: 0 | D32: 0.59 | E32: -0.33 | F32: 0.01 | G32: 0.44 | H32: 1.13 | I32: 0.97 | J32: 1.03 | K32: 0.82 | L32: 0.43 | M32: 0.64

Sheet Data Sheet 2
E1: make changes according to the Column TO THIS SHEET
C2: 42064 | D2: 42430 | E2: 42795 | F2: 43160 | G2: 43525 | H2: 43891 | I2: 44256 | J2: 44621 | K2: 44986 | L2: 45352 | M2: 45717 | N2: 46082
B3: Equity Capital | C3: 186 | D3: 186 | E3: 187 | F3: 280 | G3: 281 | H3: 281 | I3: 281 | J3: 281 | K3: 281 | L3: 275 | M3: 275 | N3: 275
B4: Reserves | C4: 40723 | D4: 43994 | E4: 50030 | F4: 54623 | G4: 62094 | H4: 66442 | I4: 75588 | J4: 82127 | K4: 89045 | L4: 86084 | M4: 97381 | N4: 109015
B5: Borrowings - | C5: 93630 | D5: 88135 | E5: 93954 | F5: 107524 | G5: 125555 | H5: 143174 | I5: 134629 | J5: 125508 | K5: 120650 | L5: 116322 | M5: 132409 | N5: 125497
B6: Long term Borrowings | C6: 68469 | D6: 61224 | E6: 67341 | F6: 72915 | G6: 74121 | H6: 82331 | I6: 82120 | J6: 61618 | K6: 61218 | L6: 56507 | M6: 57503 | N6: 63739
B7: Short term Borrowings | C7: 16729 | D7: 14897 | E7: 16534 | F7: 19332 | G7: 29224 | H7: 35021 | I7: 27766 | J7: 30477 | K7: 30896 | L7: 27834 | M7: 35861 | N7: 34779
B8: Lease Liabilities | C8: 0 | D8: 0 | E8: 0 | F8: 0 | G8: 0 | H8: 2167 | I8: 2024 | J8: 2040 | K8: 2137 | L8: 2282 | M8: 2850 | N8: 3814
B9: Preference Capital | C9: 0 | D9: 1313 | E9: 1147 | F9: 905 | G9: 976 | H9: 1404 | I9: 1124 | J9: 216 | K9: 0 | L9: 0 | M9: 0 | N9: 0
B10: Other Borrowings | C10: 8431 | D10: 10702 | E10: 8932 | F10: 14372 | G10: 21234 | H10: 22251 | I10: 21596 | J10: 31157 | K10: 26399 | L10: 29699 | M10: 36195 | N10: 23166
B11: Other Liabilities - | C11: 58727 | D11: 61775 | E11: 67400 | F11: 80812 | G11: 90106 | H11: 96790 | I11: 99597 | J11: 111112 | K11: 119745 | L11: 136921 | M11: 149050 | N11: 217596
B12: Non controlling int | C12: 4999 | D12: 2893 | E12: 3564 | F12: 5201 | G12: 6826 | H12: 9521 | I12: 12052 | J12: 12966 | K12: 14241 | L12: 16190 | M12: 17748 | N12: 19241
B13: Trade Payables | C13: 24650 | D13: 27004 | E13: 30295 | F13: 37797 | G13: 42995 | H13: 43644 | I13: 45745 | J13: 51366 | K13: 49784 | L13: 53293 | M13: 52459 | N13: 69456
B14: Advance from Customers | C14: 18502 | D14: 21376 | E14: 13956 | F14: 14860 | G14: 17271 | H14: 16353 | I14: 15876 | J14: 17963 | K14: 20425 | L14: 26875 | M14: 29087 | N14: 39586
... B39: Total Assets | C39: 193266 | D39: 194091 | E39: 211571 | F39: 243240 | G39: 278036 | H39: 306687 | I39: 310095 | J39: 319028 | K39: 329722 | L39: 339602 | M39: 379114 | N39: 452383

Sheet Relative Data
E1: MC/CMP | H1: MC+DBT-EV | L1: ev/ev/ebitda | M1: market cap/pe
B2: S.No. | C2: Name | D2: CMP Rs. | E2: no of equity share | F2: Mar Cap Rs.Cr. | G2: Debt Rs.Cr. | H2: Cash | I2: Net Debt | J2: EV Rs.Cr. | K2: Sales Rs.Cr. | L2: EBITDA | M2: NP | O2: P/E | P2: Debt / Eq | Q2: OPM % | R2: EV / EBITDA | S2: Ind PE
B3: 1 | C3: Larsen & Tourbo | D3: ='Data Sheet'!B8 -> 3785.6 | E3: ='Data Sheet'!B6 -> 137.5294 | F3: ='Data Sheet'!B9 -> 520631.29 | G3: =SUM('Raw FS'!N7:N9) -> 102332 | H3: ='Data Sheet'!K69 -> 20847.67 | I3: =G3-H3 -> 81484.33 | J3: =F3+I3 -> 602115.62 | K3: =HistoricalFS!L6 -> 285874.36 | L3: ='Data Sheet'!K34 -> 37321.09 | M3: ='Data Sheet'!K30 -> 16083.99 | O3: =F3/M3 -> 32.369536 | P3: ='Beta - Comps'!G4 -> 0.19655369 | Q3: =(('Data Sheet'!K34-'Data Sheet'!K26)/'Data Sheet'!K17)*100 -> 11.52826 | R3: =J3/L3 -> 16.133388 | S3: 38.25
B4: 2 | C4: Rail Vikas | D4: 226.2 | E4: =F4/D4 -> 208.50195 | F4: 47163.14 | G4: 4818.49 | H4: =F4+G4-J4 -> 968.25 | I4: =G4-H4 -> 3850.24 | J4: 51013.38 | K4: 20412.12 | L4: =J4/R4 -> 1636.6179 | M4: =F4/O4 -> 875.01187 | O4: 53.9 | P4: 0.49 | Q4: 3.76 | R4: 31.17 | S4: 16.91
B5: 3 | C5: NBCC | D5: 95.25 | E5: =F5/D5 -> 270 | F5: 25717.5 | G5: 0.26 | H5: =F5+G5-J5 -> 6515.62 | I5: =G5-H5 -> -6515.36 | J5: 19202.14 | K5: 12888.61 | L5: =J5/R5 -> 924.06833 | M5: =F5/O5 -> 661.96911 | O5: 38.85 | P5: 0 | Q5: 4.79 | R5: 20.78 | S5: 16.91
B6: 4 | C6: IRB Infra.Devl. | D6: 19.67 | E6: =F6/D6 -> 1207.7997 | F6: 23757.42 | G6: 20027.06 | H6: =F6+G6-J6 -> 1910.96 | I6: =G6-H6 -> 18116.1 | J6: 41873.52 | K6: 7648.15 | L6: =J6/S6 -> 2476.2578 | M6: =F6/O6 -> 879.25315 | O6: 27.02 | P6: 0.96 | Q6: 52.06 | R6: 10 | S6: 16.91
B7: 5 | C7: Cemindia Project | D7: 1369.1 | E7: =F7/D7 -> 17.178745 | F7: 23519.42 | G7: 1001.23 | H7: =F7+G7-J7 -> 948.85 | I7: =G7-H7 -> 52.38 | J7: 23571.8 | K7: 10060.58 | L7: =J7/S7 -> 1393.9562 | M7: =F7/O7 -> 588.42682 | O7: 39.97 | P7: 0.42 | Q7: 10.1 | R7: 19.88 | S7: 16.91
B8: 6 | C8: Kalpataru Proj. | D8: 1284.55 | E8: =F8/D8 -> 17.077249 | F8: 21936.58 | G8: 3542.62 | H8: =F8+G8-J8 -> 1842.19 | I8: =G8-H8 -> 1700.43 | J8: 23637.01 | K8: 27143.06 | L8: =J8/S8 -> 1397.8125 | M8: =F8/O8 -> 977.56595 | O8: 22.44 | P8: 0.46 | Q8: 8.96 | R8: 9.35 | S8: 16.91

Sheet Sheet1

Sheet List Of Stocks
B2: COMPANY_NAME | C2: BSE | D2: NSE | E2: Industry
B3: 20 MICRONS LTD | C3: 533022 | D3: 20MICRONS | E3: Mining
B4: 21ST CENTURY MANAGEMENT SERVICES LTD | C4: 526921 | D4: 21STCENMGM | E4: Other Financial Services
B5: 3I INFOTECH LTD | C5: 532628 | D5: 3IINFOTECH | E5: IT Consulting & Software
B6: 3M (INDIA) LTD | C6: 523395 | D6: 3M(INDIA) | E6: Diversified
B7: 3M INDIA LTD | C7: 523395 | D7: 3MINDIA | E7: Diversified
B8: 3P LAND HOLDINGS LTD | C8: 516092 | D8: 3PLAND | E8: Paper & Paper Products
B9: 5PAISA CAPITAL LTD | C9: 540776 | D9: 5PAISA | E9: Other Financial Services
B10: 63 MOONS TECHNOLOGIES LTD | C10: 526881 | D10: 63MOONS | E10: IT Consulting & Software
B11: 7NR RETAIL LTD | C11: 540615 | D11: Not Listed | E11: Specialty Retail
B12: 7SEAS ENTERTAINMENT LTD | C12: 540874 | D12: Not Listed | E12: Movies & Entertainment
B13: 8K MILES SOFTWARE SERVICES LTD | C13: 512161 | D13: 8KMILES | E13: Internet Software & Services
B14: A & M FEBCON LTD | C14: 540697 | D14: Not Listed | E14: Industrial Machinery
B15: A AND M JUMBO BAGS LTD | C15: Not Listed | D15: AMJUMBO | E15: SME
B16: A INFRASTRUCTURE LTD | C16: 539620 | D16: Not Listed | E16: Cement & Cement Products
B17: A K SPINTEX LTD | C17: 539300 | D17: Not Listed | E17: Textiles
B18: A K CAPITAL SERVICES LTD | C18: 530499 | D18: Not Listed | E18: Finance (including NBFCs)
B19: A.F. Enterprises Ltd | C19: 538351 | D19: AFEL | E19: Investment Companies
B20: A-1 ACID LTD | C20: 542012 | D20: Not Listed | E20: Comm.Trading & Distribution
B21: A2Z INFRA ENGINEERING LTD | C21: 533292 | D21: A2ZINFRA | E21: Utilities:Non-Elec.
B22: AADHAAR VENTURES (INDIA) LTD | C22: 531611 | D22: Not Listed | E22: Finance (including NBFCs)
B23: AADHAAR VENTURES INDIA LTD | C23: 531611 | D23: Not Listed | E23: Finance (including NBFCs)
B24: AAKASH EXPLORATION SERVICES LTD | C24: Not Listed | D24: AAKASH | E24: SME
B25: AANANDA LAKSHMI SPINNING MILLS LTD | C25: 539096 | D25: Not Listed | E25: Textiles
B26: AANCHAL ISPAT LTD | C26: 538812 | D26: Not Listed | E26: Iron & Steel/Interm.Products
B27: AAR COMMERCIAL COMPANY LTD | C27: 539632 | D27: Not Listed | E27: Distributors
B28: Aar Shyam India Investment Company Ltd | C28: 542377 | D28: AARSHYAM | E28: Finance (including NBFCs)
B29: AAREY DRUGS & PHARMACEUTICALS LTD | C29: 524412 | D29: Not Listed | E29: Pharmaceuticals
B30: AARON INDUSTRIES LTD | C30: Not Listed | D30: AARON | E30: SME
B31: Aartech Solonics Ltd | C31: 542580 | D31: AARTECH | E31: Heavy Electrical Equipment
B32: AARTI DRUGS LTD | C32: 524348 | D32: AARTIDRUGS | E32: Pharmaceuticals
B33: AARTI INDUSTRIES LTD | C33: 524208 | D33: AARTIIND | E33: Commodity Chemicals
B34: AARV INFRATEL LTD | C34: 526488 | D34: Not Listed | E34: Textiles
B35: AARVEE DENIMS & EXPORTS LTD | C35: 514274 | D35: AARVEEDEN | E35: Textiles
B36: AARVI ENCON LTD | C36: Not Listed | D36: AARVI | E36: SME
B37: AASHEE INFOTECH LTD | C37: 519319 | D37: Not Listed | E37: Internet Software & Services
B38: AASWA TRADING & EXPORTS LTD | C38: 512038 | D38: Not Listed | E38: Comm.Trading & Distribution
B39: AAVAS FINANCIERS LTD | C39: 541988 | D39: AAVAS | E39: Housing Finance
B40: AAYUSH FOOD AND HERBS LTD | C40: 539528 | D40: Not Listed | E40: Packaged Foods
B41: ABAN OFFSHORE LTD | C41: 523204 | D41: ABAN | E41: Exploration & Production
B42: ABANS ENTERPRISES LTD | C42: 512165 | D42: Not Listed | E42: Comm.Trading & Distribution
B43: ABB INDIA LTD | C43: 500002 | D43: ABB | E43: Heavy Electrical Equipment
B44: ABBOTT (INDIA) LTD | C44: 500488 | D44: ABBOT(INDIA) | E44: Pharmaceuticals
B45: ABBOTT INDIA LTD | C45: 500488 | D45: ABBOTINDIA | E45: Pharmaceuticals
B46: ABC (INDIA) LTD | C46: 520123 | D46: Not Listed | E46: Surface Transportation
B47: ABC GAS INTERNATIONAL LTD | C47: 513119 | D47: Not Listed | E47: Copper
B48: ABC INDIA LTD | C48: 520123 | D48: Not Listed | E48: Surface Transportation
... B56: ABIRAMI FINANCIAL SERVICES INDIA LTD | C56: 511756 | D56: Not Listed | E56: Finance (including NBFCs)
B57: ABM INTERNATIONAL LTD | C57: Not Listed | D57: ABMINTLTD | E57: Others
B58: ABM KNOWLEDGEWARE LTD | C58: 531161 | D58: Not Listed | E58: IT Software Products
B59: ACC LTD | C59: 500410 | D59: ACC | E59: Cement & Cement Products
B60: ACCEL LTD | C60: 517494 | D60: Not Listed | E60: Storage Media & Peripherals
B61: ACCELYA KALE SOLUTIONS LTD | C61: 532268 | D61: ACCELYA | E61: IT Consulting & Software
B62: ACCORD SYNERGY LTD | C62: Not Listed | D62: ACCORD | E62: SME
B63: ACCURACY SHIPPING LTD | C63: Not Listed | D63: ACCURACY | E63: SME
B64: ACE EDUTREND LTD | C64: 530093 | D64: Not Listed | E64: Education
B65: ACE INTEGRATED SOLUTIONS LTD | C65: Not Listed | D65: ACEINTEG | E65: SME
B66: ACE MEN ENGG WORKS LTD | C66: 539661 | D66: Not Listed | E66: Distributors
B67: ACE SOFTWARE EXPORTS LTD | C67: 531525 | D67: Not Listed | E67: IT Software Products
B68: Achal Investments Ltd | C68: 538570 | D68: ACHAL | E68: Other Financial Services
B69: ACI INFOCOM LTD | C69: 517356 | D69: Not Listed | E69: Storage Media & Peripherals
B70: ACKNIT INDUSTRIES LTD | C70: 530043 | D70: Not Listed | E70: Other Apparels & Accessories
B71: ACME RESOURCES LTD | C71: 539391 | D71: Not Listed | E71: Finance (including NBFCs)
B72: ACROW INDIA LTD. | C72: 513149 | D72: ACROW | E72: Iron &amp; Steel Products
B73: ACRYSIL LTD | C73: 524091 | D73: Not Listed | E73: Plastic Products
B74: ACTION CONSTRUCTION EQUIPMENT LTD | C74: 532762 | D74: ACE | E74: Transport Related Services
B75: ACTION FINANCIAL SERVICES (INDIA) LTD | C75: 511706 | D75: Not Listed | E75: Other Financial Services
B76: ACTION FINANCIAL SERVICES INDIA LTD | C76: 511706 | D76: Not Listed | E76: Other Financial Services
B77: ACTIVE CLOTHING CO LTD | C77: 541144 | D77: Not Listed | E77: Other Apparels & Accessories
... B135: AGRI-TECH INDIA LTD | C135: 537292 | D135: AGRITECH | E135: Other Agricultural Products
B136: AGRO PHOS (INDIA) LTD | C136: Not Listed | D136: AGROPHOS | E136: SME
B137: AGRO PHOS INDIA LTD | C137: Not Listed | D137: AGROPHOS | E137: SME
B138: AGRO TECH FOODS LTD | C138: 500215 | D138: ATFL | E138: Other Agricultural Products
B139: AHIMSA INDUSTRIES LTD | C139: Not Listed | D139: AHIMSA | E139: SME
B140: AHLADA ENGINEERS LTD | C140: Not Listed | D140: AHLADA | E140: SME
B141: AHLUWALIA CONTRACTS (INDIA) LTD | C141: 532811 | D141: AHLUCONT | E141: Realty
B142: AHLUWALIA CONTRACTS INDIA LTD | C142: 532811 | D142: AHLUCONT | E142: Realty
B143: AHMEDABAD STEELCRAFT LTD | C143: 522273 | D143: Not Listed | E143: Iron & Steel/Interm.Products
B144: AI CHAMPDANY INDUSTRIES LTD | C144: 532806 | D144: Not Listed | E144: Jute & Jute Products
B145: AIA ENGINEERING LTD | C145: 532683 | D145: AIAENG | E145: Other Industrial Goods
B146: AIMCO PESTICIDES LTD | C146: 524288 | D146: Not Listed | E146: Agrochemicals
B147: AIRAN LTD | C147: Not Listed | D147: AIRAN | E147: SME
B148: AIRO LAM LTD | C148: Not Listed | D148: AIROLAM | E148: SME
B149: AISHWARYA TELECOM LTD | C149: 532975 | D149: Not Listed | E149: Telecom Equipment
B150: AJANTA PHARMA LTD | C150: 532331 | D150: AJANTPHARM | E150: Pharmaceuticals
B151: AJANTA SOYA LTD | C151: 519216 | D151: Not Listed | E151: Edible Oils
B152: AJCON GLOBAL SERVICES LTD | C152: 511692 | D152: Not Listed | E152: Other Financial Services
B153: AJEL LTD | C153: 530713 | D153: Not Listed | E153: IT Consulting & Software
B154: AJMERA REALTY & INFRA (INDIA) LTD | C154: 513349 | D154: AJMERA | E154: Realty
B155: AJMERA REALTY & INFRA INDIA LTD | C155: 513349 | D155: AJMERA | E155: Realty
B156: AJOONI BIOTECH LTD | C156: Not Listed | D156: AJOONI | E156: SME
B157: AJWA FUN WORLD & RESORT LTD | C157: 526628 | D157: Not Listed | E157: Other Leisure Facilities
B158: AKAR AUTO INDUSTRIES LTD | C158: 530621 | D158: Not Listed | E158: Industrial Machinery
B159: AKASH INFRA PROJECTS LTD | C159: Not Listed | D159: AKASH | E159: SME
B160: AKASHDEEP METAL INDUSTRIES LTD | C160: 538778 | D160: Not Listed | E160: Finance (including NBFCs)
B161: AKG EXIM LTD | C161: Not Listed | D161: AKG | E161: SME
B162: AKI (INDIA) LTD | C162: 542020 | D162: Not Listed | E162: Other Apparels & Accessories
B163: AKI INDIA LTD | C163: 542020 | D163: Not Listed | E163: Other Apparels & Accessories
B164: AKM LACE AND EMBROTEX LTD | C164: 540718 | D164: Not Listed | E164: Textiles
B165: AKME STAR HOUSING FINANCE LTD | C165: 539017 | D165: Not Listed | E165: Housing Finance
...
